Workbook

Sheet data
A1: source_target | B1: source_thematic_area | C1: source_target_subtheme | D1: source_target_content | E1: impact_target | F1: impact_thematic_area | G1: impact_target_subtheme | H1: impact_target_content | I1: impact_type | J1: impact_color | K1: impact_weight | L1: LLM_justification | M1: expert_comments | N1: expert | O1: expert_confidence_level
A2: TA2.41 | B2: TA2 - Clean, affordable and secure energy | C2: Energy Efficiency | D2: Member States are required to achieve cumulative end-use energy savings from 2021 to 2030, equivalent to new annual savings of at least 0.8% of final energy consumption in 2021-2023, at least 1.3% in 2024-2025, 1.5% in 2026-2027 and 1.9% in 2028-2030 | E2: TA3.3 | F2: TA3 - Industrial strategy for a clean and circular economy | G2: Circularity/Recycling | H2: Double EUcircular material use rate in the coming decade | I2: + | J2: #1FA139 | K2: 2 | L2: The implementation of TA2.41, which aims to achieve cumulative end-use energy savings, may reinforce TA3.3, which aims to double the EU's circular material use rate, as increased energy efficiency can lead to reduced material consumption and waste generation, thus supporting the transition to a more circular economy. | N2: Castellazzi Luca | O2: 8
A3: TA2.22 | B3: TA2 - Clean, affordable and secure energy | C3: Energy Efficiency | D3: Member States shall collectively ensure a reduction of energy consumption of at least 11.7% in 2030 compared to the projections of the 2020 EU Reference Scenario | E3: TA1.3 | F3: TA1 - Climate ambition | G3: GHG Reduction | H3: Reduce by at least 55% net GHG emissions compared to 1990 levels, by 2030 | I3: + | J3: #1FA139 | K3: 3 | L3: The implementation of TA2.22 may help the achievement of TA1.3, as reducing energy consumption may not be sufficient to achieve the GHG emissions reduction target. | M3: The implementation of TA2.22 will strongly contribute to the achievement of TA1.3 | N3: Castellazzi Luca | O3: 8
A4: TA2.41 | B4: TA2 - Clean, affordable and secure energy | C4: Energy Efficiency | D4: Member States are required to achieve cumulative end-use energy savings from 2021 to 2030, equivalent to new annual savings of at least 0.8% of final energy consumption in 2021-2023, at least 1.3% in 2024-2025, 1.5% in 2026-2027 and 1.9% in 2028-2030 | E4: TA1.3 | F4: TA1 - Climate ambition | G4: GHG Reduction | H4: Reduce by at least 55% net GHG emissions compared to 1990 levels, by 2030 | I4: + | J4: #1FA139 | K4: 2 | L4: The implementation of TA2.41 may help the achievement of TA1.3, as increasing energy savings may lead to increased energy demand, which could hinder the reduction of GHG emissions. | N4: Castellazzi Luca | O4: 8
A5: TA2.22 | B5: TA2 - Clean, affordable and secure energy | C5: Energy Efficiency | D5: Member States shall collectively ensure a reduction of energy consumption of at least 11.7% in 2030 compared to the projections of the 2020 EU Reference Scenario | E5: TA5.11 | F5: TA5 - Greening the Common Agricultural Policy - Farm to Fork Strategy | G5: Biodiversity Protection & Conservation | H5: Biodiversity conservation and restoration of natural resources: Protect the environment and restore natural resources. Preserve biodiversity and reduce biodiversity loss. | I5: + | J5: #1FA139 | K5: 2 | L5: The collective effort to reduce energy consumption, as stated in TA2.22, can reinforce the objectives of TA5.11 by decreasing the EU's energy footprint, promoting sustainable food production, and conserving biodiversity. | N5: Castellazzi Luca | O5: 8
A6: TA2.41 | B6: TA2 - Clean, affordable and secure energy | C6: Energy Efficiency | D6: Member States are required to achieve cumulative end-use energy savings from 2021 to 2030, equivalent to new annual savings of at least 0.8% of final energy consumption in 2021-2023, at least 1.3% in 2024-2025, 1.5% in 2026-2027 and 1.9% in 2028-2030 | E6: TA5.11 | F6: TA5 - Greening the Common Agricultural Policy - Farm to Fork Strategy | G6: Biodiversity Protection & Conservation | H6: Biodiversity conservation and restoration of natural resources: Protect the environment and restore natural resources. Preserve biodiversity and reduce biodiversity loss. | I6: + | J6: #1FA139 | K6: 2 | L6: The implementation of TA2.41, which aims to achieve cumulative end-use energy savings, can positively impact TA5.11 by reducing energy consumption and promoting sustainable practices in the food system, thus supporting biodiversity conservation and restoration of natural resources. | N6: Castellazzi Luca | O6: 8
A7: TA2.41 | B7: TA2 - Clean, affordable and secure energy | C7: Energy Efficiency | D7: Member States are required to achieve cumulative end-use energy savings from 2021 to 2030, equivalent to new annual savings of at least 0.8% of final energy consumption in 2021-2023, at least 1.3% in 2024-2025, 1.5% in 2026-2027 and 1.9% in 2028-2030 | E7: TA6.1 | F7: TA6 - Preserving and protecting biodiversity | G7: Biodiversity Protection & Conservation | H7: 1.a Legally protect a minimum of 30% of the EU land area | I7: + | J7: #1FA139 | K7: 2 | L7: The implementation of TA2.41, which aims to achieve cumulative end-use energy savings, may reinforce TA6.1 by promoting the protection of at least 30% of the EU's land area, as the reduction of energy consumption can lead to lower land-use pressures and help preserve natural habitats. | N7: Castellazzi Luca | O7: 8
A8: TA2.41 | B8: TA2 - Clean, affordable and secure energy | C8: Energy Efficiency | D8: Member States are required to achieve cumulative end-use energy savings from 2021 to 2030, equivalent to new annual savings of at least 0.8% of final energy consumption in 2021-2023, at least 1.3% in 2024-2025, 1.5% in 2026-2027 and 1.9% in 2028-2030. Directive (EU) 2023/1791 | E8: TA7.9 | F8: TA7 - Towards a zero-pollution ambition for a toxic free environment | G8: Improve Air Quality | H8: Improve air quality to reduce the number of premature deaths caused by air pollution by 55% by 2030 | I8: + | J8: #1FA139 | K8: 2 | L8: The implementation of TA2.41 will lead to a reduction in energy consumption, which in turn will reduce the amount of pollutants released into the air, thus improving air quality and reducing premature deaths caused by air pollution, as stated in TA7.9. | M8: ok | N8: Castellazzi Luca | O8: 8
A9: TA2.22 | B9: TA2 - Clean, affordable and secure energy | C9: Energy Efficiency | D9: Member States shall collectively ensure a reduction of energy consumption of at least 11.7% in 2030 compared to the projections of the 2020 EU Reference Scenario | E9: TA7.13 | F9: TA7 - Towards a zero-pollution ambition for a toxic free environment | G9: Improve Air Quality | H9: Reduce by 25% the EU ecosystems where air pollution threatens biodiversity, by 2030 | I9: + | J9: #1FA139 | K9: 2 | L9: The reduction in energy consumption, as stated in TA2.22, will lead to a decrease in air pollution, which in turn will reduce the number of EU ecosystems where air pollution threatens biodiversity, thus supporting the objective of TA7.13. | N9: Castellazzi Luca | O9: 8
A10: TA2.41 | B10: TA2 - Clean, affordable and secure energy | C10: Energy Efficiency | D10: Member States are required to achieve cumulative end-use energy savings from 2021 to 2030, equivalent to new annual savings of at least 0.8% of final energy consumption in 2021-2023, at least 1.3% in 2024-2025, 1.5% in 2026-2027 and 1.9% in 2028-2030. Directive (EU) 2023/1791 | E10: TA7.15 | F10: TA7 - Towards a zero-pollution ambition for a toxic free environment | G10: Improve Soils Health | H10: Having all soils in healthy condition by 2050 | I10: + | J10: #1FA139 | K10: 1 | L10: The implementation of TA2.41 will lead to a reduction in energy consumption, which in turn will reduce the amount of pollutants released into the soil, thus improving soil quality and contributing to the objective of having all soils in healthy condition by 2050, as stated in TA7.15. | N10: Castellazzi Luca | O10: 8
A11: TA2.41 | B11: TA2 - Clean, affordable and secure energy | C11: Energy Efficiency | D11: Member States are required to achieve cumulative end-use energy savings from 2021 to 2030, equivalent to new annual savings of at least 0.8% of final energy consumption in 2021-2023, at least 1.3% in 2024-2025, 1.5% in 2026-2027 and 1.9% in 2028-2030. Directive (EU) 2023/1791 | E11: TA7.9 | F11: TA7 - Towards a zero-pollution ambition for a toxic free environment | G11: Improve Air Quality | H11: Improve air quality to reduce the number of premature deaths caused by air pollution by 55% by 2030 | I11: + | J11: #1FA139 | K11: 2 | L11: The reduction of energy consumption will help to minimize the environmental impacts of energy production, making it more feasible to achieve the air quality targets. | M11: duplication? | N11: Castellazzi Luca | O11: 8
A12: TA2.22 | B12: TA2 - Clean, affordable and secure energy | C12: Energy Efficiency | D12: Member States shall collectively ensure a reduction of energy consumption of at least 11.7% in 2030 compared to the projections of the 2020 EU Reference Scenario | E12: TA7.13 | F12: TA7 - Towards a zero-pollution ambition for a toxic free environment | G12: Improve Air Quality | H12: Reduce by 25% the EU ecosystems where air pollution threatens biodiversity, by 2030 | I12: + | J12: #1FA139 | K12: 2 | L12: The reduction of energy consumption will help to minimize the environmental impacts of energy production, making it more feasible to achieve the biodiversity targets. | M12: duplication? | N12: Castellazzi Luca | O12: 8
A13: TA4.34 | B13: TA4 - Sustainable and smart mobility | C13: Energy Efficiency | D13: Member States shall ensure that a minimum shore-side electricity supply for seagoing container ships and seagoing passenger ships is provided in TEN-T maritime ports. To that end, by 31 December 2029 TEN-T core and comprehensive maritime ports [...] are equipped to provide each year shore-side electricity supply for at least 90 % of the total number of port calls of seagoing container ships above 5.000 gross tonnes that are moored at the quayside at the maritime port concerned and 90% of the total number of port calls of seagoing ro-ro passenger ships above 5.000 gross tonnes and seagoing high-speed passenger craft above 5.000 gross tonnes that are moored at the quayside at the maritime port concerned Regulation (EU) 2023/1804 | E13: TA6.34 | F13: TA6 - Preserving and protecting biodiversity | G13: Biodiversity Protection & Conservation - Monitoring | H13: Terrestrial, coastal and freshwater ecosystems. Member States shall ensure that condition is known for at least 90% of the area distributed overall habitat types listed in Annex I by 2030 and 100% by 2040. | I13: + | J13: #1FA139 | K13: 1 | L13: The provision of shore-side electricity supply could support the protection of marine ecosystems and habitats, potentially contributing to the knowledge of the condition of terrestrial, coastal, and freshwater ecosystems. | N13: Castellazzi Luca | O13: 8
A14: TA4.10 | B14: TA4 - Sustainable and smart mobility | C14: Energy Efficiency | D14: EU fisheries are encouraged to continue the positive trend, as observed for the period 2009-2019, towards reducing fuel intensity by reducing the fossil-fuel consumption per kg of landed product for at least an additional 15% for the period 2019-2030. Energy Transition of the EU Fisheries and Aquaculture sector | E14: TA5.30 | F14: TA5 - Greening the Common Agricultural Policy - Farm to Fork Strategy | G14: Food affordability | H14: Food affordability: Ensure affordability to sufficient, nutritious and sustainable food | I14: + | J14: #1FA139 | K14: 2 | L14: The reduction of fuel intensity in the fisheries sector can support the development of sustainable and resilient food systems by promoting the use of renewable energy sources and reducing greenhouse gas emissions, which can contribute to ensuring food affordability. | N14: Castellazzi Luca | O14: 8
A15: TA1.8 | B15: TA1 - Climate ambition | C15: Energy Efficiency | D15: Reach energy neutrality in the wastewater treatment sector by 2045. | E15: TA7.9 | F15: TA7 - Towards a zero-pollution ambition for a toxic free environment | G15: Improve Air Quality | H15: Improve air quality to reduce the number of premature deaths caused by air pollution by 55% by 2030 | I15: + | J15: #1FA139 | K15: 2 | L15: Reaching energy neutrality in the wastewater treatment sector will enable the improvement of air quality, as it will lead to a decrease in energy consumption and emissions, thus reducing air pollution. | N15: Castellazzi Luca | O15: 8
A16: TA1.8 | B16: TA1 - Climate ambition | C16: Energy Efficiency | D16: Reach energy neutrality in the wastewater treatment sector by 2045 | E16: TA7.5 | F16: TA7 - Towards a zero-pollution ambition for a toxic free environment | G16: Improve Water Quality | H16: The revised Urban Wastewater Treatment Directive (UWWTD) extends the scope of the 1991 UWWTD | I16: + | J16: #1FA139 | K16: 1 | L16: The revised UWWTD will contribute to reaching energy neutrality in the wastewater treatment sector by 2045. | N16: Castellazzi Luca | O16: 8
A17: TA2.41 | B17: TA2 - Clean, affordable and secure energy | C17: Energy Efficiency | D17: Member States are required to achieve cumulative end-use energy savings from 2021 to 2030, equivalent to new annual savings of at least 0.8% of final energy consumption in 2021-2023, at least 1.3% in 2024-2025, 1.5% in 2026-2027 and 1.9% in 2028-2030 | E17: TA3.31 | F17: TA3 - Industrial strategy for a clean and circular economy | G17: Circularity/Recycling - Municipal Waste | H17: Member States shall take the necessary measures to attain the recycling targets of 65% by weight of all packaging waste generated by 31 December 2025, and of 70% by weight of all packaging waste generated by 31 December 2030. Proposal on packaging and packaging waste | I17: + | J17: #1FA139 | K17: 2 | L17: The implementation of TA2.41 may enable TA3.31, which aims to increase recycling targets for packaging waste, as increased energy efficiency and reduced energy consumption may lead to reduced packaging waste generation, thus supporting the transition to a more circular economy. | N17: Castellazzi Luca | O17: 8
A18: TA2.22 | B18: TA2 - Clean, affordable and secure energy | C18: Energy Efficiency | D18: Member States shall collectively ensure a reduction of energy consumption of at least 11.7% in 2030 compared to the projections of the 2020 EU Reference Scenario | E18: TA4.18 | F18: TA4 - Sustainable and smart mobility | G18: Biofuels | H18: The share of biofuels and biogas produced from the feedstock listed in Part B of Annex IX in the energy content of fuels and electricity supplied to the transport sector shall, except in Cyprus and Malta, be limited to 1.7%. Directive (EU) 2023/2413 | I18: - | J18: #DA2620 | K18: 1 | L18: The implementation of TA2.22, which aims to reduce energy consumption, may have a negative impact on TA4.18, which limits the share of biofuels and biogas produced from certain feedstocks. By reducing energy consumption, TA2.22 may lead to decreased production of biofuels and biogas, thus hindering the achievement of TA4.18. | N18: Castellazzi Luca | O18: 8
A19: TA2.21 | B19: TA2 - Clean, affordable and secure energy | C19: Energy Efficiency | D19: Member States shall ensure that the total final energy consumption of all public bodies combined is reduced by at least 1.9% each year, when compared to 2021 | E19: TA1.3 | F19: TA1 - Climate ambition | G19: GHG Reduction | H19: Reduce by at least 55% net GHG emissions compared to 1990 levels, by 2030 | I19: + | J19: #1FA139 | K19: 3 | L19: The implementation of TA2.21 may enable the achievement of TA1.3, as reducing energy consumption in public bodies may not be sufficient to achieve the GHG emissions reduction target. | N19: Castellazzi Luca | O19: 8
A20: TA2.23 | B20: TA2 - Clean, affordable and secure energy | C20: Energy Efficiency | D20: Member States shall make efforts to collectively contribute to the indicative Union primary energy consumption target amounting to no more than 992.5 Mtoe in 2030 | E20: TA1.3 | F20: TA1 - Climate ambition | G20: GHG Reduction | H20: Reduce by at least 55% net GHG emissions compared to 1990 levels, by 2030 | I20: + | J20: #1FA139 | K20: 3 | L20: The implementation of TA2.23 may enable the achievement of TA1.3, as reducing primary energy consumption may not be sufficient to achieve the GHG emissions reduction target. | N20: Castellazzi Luca | O20: 8
A21: TA2.41 | B21: TA2 - Clean, affordable and secure energy | C21: Energy Efficiency | D21: Member States are required to achieve cumulative end-use energy savings from 2021 to 2030, equivalent to new annual savings of at least 0.8% of final energy consumption in 2021-2023, at least 1.3% in 2024-2025, 1.5% in 2026-2027 and 1.9% in 2028-2030 | E21: TA4.1 | F21: TA4 - Sustainable and smart mobility | G21: Biofuels | H21: Achieve an annual production of sustainable biomethane of 35 billion cubic meters by 2030 | I21: + | J21: #1FA139 | K21: 1 | L21: The implementation of TA2.41, which aims to achieve cumulative end-use energy savings, may have a positive impact on TA4.1, which targets the production of sustainable biomethane. By reducing energy consumption, TA2.41 can lead to increased availability of biomass for biomethane production, thus supporting the achievement of TA4.1. | N21: Castellazzi Luca | O21: 8
A22: TA2.21 | B22: TA2 - Clean, affordable and secure energy | C22: Energy Efficiency | D22: Member States shall ensure that the total final energy consumption of all public bodies combined is reduced by at least 1.9% each year, when compared to 2021 | E22: TA5.11 | F22: TA5 - Greening the Common Agricultural Policy - Farm to Fork Strategy | G22: Biodiversity Protection & Conservation | H22: Biodiversity conservation and restoration of natural resources: Protect the environment and restore natural resources. Preserve biodiversity and reduce biodiversity loss. | I22: + | J22: #1FA139 | K22: 1 | L22: The reduction of energy consumption in public bodies, as per TA2.21, can contribute to the conservation and restoration of natural resources, as outlined in TA5.11, by minimizing the environmental footprint of public institutions (and promoting sustainable food systems?) | M22: mah…. | N22: Castellazzi Luca | O22: 8
A23: TA2.21 | B23: TA2 - Clean, affordable and secure energy | C23: Energy Efficiency | D23: Member States shall ensure that the total final energy consumption of all public bodies combined is reduced by at least 1.9% each year, when compared to 2021 | E23: TA7.4 | F23: TA7 - Towards a zero-pollution ambition for a toxic free environment | G23: Improve Air Quality | H23: The Industrial Emissions Directive (IED) aims at preventing or reducing emissions from large industrial installations and intensive farming into the environment. | I23: + | J23: #1FA139 | K23: 1 | L23: The reduction of energy consumption will help to minimize the environmental impacts of public activities, making it more feasible to achieve the emissions reduction targets. | N23: Castellazzi Luca | O23: 8
A24: TA4.33 | B24: TA4 - Sustainable and smart mobility | C24: Energy Efficiency | D24: Member States shall ensure that at least one installation providing shore-side electricity supply to inland waterway vessels is deployed at all TEN-T core inland waterway ports by 1 January 2025, at least one installation providing shore-side electricity supply to inland waterway vessels is deployed at all TEN-T comprehensive inland waterway ports by 1 January 2030. Regulation (EU) 2023/1804 | E24: TA2.22 | F24: TA2 - Clean, affordable and secure energy | G24: Energy Efficiency | H24: Member States shall collectively ensure a reduction of energy consumption of at least 11.7% in 2030 compared to the projections of the 2020 EU Reference Scenario | I24: + | J24: #1FA139 | K24: 1 | L24: The implementation of TA4.33 could enable the achievement of TA2.22 by reducing energy consumption in the inland waterway sector, thus allowing for a greater share of renewable energy in the energy mix. | M24: to be replaced with: The implementation of TA4.33 could enable the achievement of TA2.22 by reducing energy consumption in the inland waterway sector. | N24: Castellazzi Luca | O24: 8
A25: TA4.10 | B25: TA4 - Sustainable and smart mobility | C25: Energy Efficiency | D25: EU fisheries are encouraged to continue the positive trend, as observed for the period 2009-2019, towards reducing fuel intensity by reducing the fossil-fuel consumption per kg of landed product for at least an additional 15% for the period 2019-2030. Energy Transition of the EU Fisheries and Aquaculture sector | E25: TA2.23 | F25: TA2 - Clean, affordable and secure energy | G25: Energy Efficiency | H25: Member States shall make efforts to collectively contribute to the indicative Union primary energy consumption target amounting to no more than 992.5 Mtoe in 2030 | I25: + | J25: #1FA139 | K25: 1 | L25: The implementation of TA4.10 could support the achievement of TA2.23 by reducing energy consumption in the fisheries sector, thus allowing for a greater share of renewable energy in the energy mix. | N25: Castellazzi Luca | O25: 8
A26: TA4.34 | B26: TA4 - Sustainable and smart mobility | C26: Energy Efficiency | D26: Member States shall ensure that a minimum shore-side electricity supply for seagoing container ships and seagoing passenger ships is provided in TEN-T maritime ports. To that end, by 31 December 2029 TEN-T core and comprehensive maritime ports [...] are equipped to provide each year shore-side electricity supply for at least 90 % of the total number of port calls of seagoing container ships above 5.000 gross tonnes that are moored at the quayside at the maritime port concerned and 90% of the total number of port calls of seagoing ro-ro passenger ships above 5.000 gross tonnes and seagoing high-speed passenger craft above 5.000 gross tonnes that are moored at the quayside at the maritime port concerned Regulation (EU) 2023/1804 | E26: TA7.14 | F26: TA7 - Towards a zero-pollution ambition for a toxic free environment | G26: Noise Reduction | H26: Reduce the share of people chronically disturbed by transport noise by 30%, by 2030 | I26: + | J26: #1FA139 | K26: 1 | L26: The provision of shore-side electricity supply for seagoing container ships and passenger ships can help reduce noise pollution from transport operations, thus reducing the number of people chronically disturbed by transport noise. | N26: Castellazzi Luca | O26: 8
A27: TA4.10 | B27: TA4 - Sustainable and smart mobility | C27: Energy Efficiency | D27: EU fisheries are encouraged to continue the positive trend, as observed for the period 2009-2019, towards reducing fuel intensity by reducing the fossil-fuel consumption per kg of landed product for at least an additional 15% for the period 2019-2030. Energy Transition of the EU Fisheries and Aquaculture sector | E27: TA7.5 | F27: TA7 - Towards a zero-pollution ambition for a toxic free environment | G27: Improve Water Quality | H27: The revised Urban Wastewater Treatment Directive (UWWTD) extends the scope of the 1991 UWWTD | I27: + | J27: #1FA139 | K27: 2 | L27: The reduction of fuel intensity in the EU fisheries sector can lead to a decrease in wastewater and pollution from fishing activities, thus contributing to improved water quality and reduced pollution. | N27: Castellazzi Luca | O27: 8
A28: TA4.33 | B28: TA4 - Sustainable and smart mobility | C28: Energy Efficiency | D28: Member States shall ensure that at least one installation providing shore-side electricity supply to inland waterway vessels is deployed at all TEN-T core inland waterway ports by 1 January 2025, at least one installation providing shore-side electricity supply to inland waterway vessels is deployed at all TEN-T comprehensive inland waterway ports by 1 January 2030. Regulation (EU) 2023/1804 | E28: TA6.28 | F28: TA6 - Preserving and protecting biodiversity | G28: Biodiversity Protection & Conservation - Fisheries | H28: In accordance with the CFP, it is crucial to continue and accelerate the work of rebuilding and keeping fish stocks above MSY levels | I28: + | J28: #1FA139 | K28: 1 | L28: The deployment of shore-side electricity supply installations could support the protection of aquatic ecosystems and the rebuilding of fish stocks. | N28: Castellazzi Luca | O28: 8
A29: TA4.34 | B29: TA4 - Sustainable and smart mobility | C29: Energy Efficiency | D29: Member States shall ensure that a minimum shore-side electricity supply for seagoing container ships and seagoing passenger ships is provided in TEN-T maritime ports. To that end, by 31 December 2029 TEN-T core and comprehensive maritime ports [...] are equipped to provide each year shore-side electricity supply for at least 90 % of the total number of port calls of seagoing container ships above 5.000 gross tonnes that are moored at the quayside at the maritime port concerned and 90% of the total number of port calls of seagoing ro-ro passenger ships above 5.000 gross tonnes and seagoing high-speed passenger craft above 5.000 gross tonnes that are moored at the quayside at the maritime port concerned Regulation (EU) 2023/1804 | E29: TA5.25 | F29: TA5 - Greening the Common Agricultural Policy - Farm to Fork Strategy | G29: Food quality - Animal Welfare | H29: Animal welfare: Promote better animal welfare to improve animal health and food quality. | I29: + | J29: #1FA139 | K29: 1 | L29: The provision of shore-side electricity supply to seagoing vessels can support the promotion of animal welfare by reducing the environmental impact of maritime transport and promoting sustainable and resilient food systems. | M29: yes, for fishes | N29: Castellazzi Luca | O29: 8
A30: TA4.10 | B30: TA4 - Sustainable and smart mobility | C30: Energy Efficiency | D30: EU fisheries are encouraged to continue the positive trend, as observed for the period 2009-2019, towards reducing fuel intensity by reducing the fossil-fuel consumption per kg of landed product for at least an additional 15% for the period 2019-2030. Energy Transition of the EU Fisheries and Aquaculture sector | E30: TA7.5 | F30: TA7 - Towards a zero-pollution ambition for a toxic free environment | G30: Improve Water Quality | H30: The revised Urban Wastewater Treatment Directive (UWWTD) extends the scope of the 1991 UWWTD | I30: + | J30: #1FA139 | K30: 1 | L30: The revised UWWTD can support the energy transition in the fisheries and aquaculture sector by reducing emissions from wastewater treatment, thus creating a more favorable environment for the reduction of fuel intensity. | N30: Castellazzi Luca | O30: 8
A31: TA4.20 | B31: TA4 - Sustainable and smart mobility | C31: Renewable Energy - Hydrogen Production | D31: In the first phase, from 2020 up to 2024, the strategic objective is to install at least 6 GW of renewable hydrogen electrolysers in the EU. In the second phase, from 2025 up to 2030, the strategic objective is to install at least 40 GW of renewable hydrogen electrolysers. A Hydrogen Strategy for a climate-neutral Europe | E31: TA2.41 | F31: TA2 - Clean, affordable and secure energy | G31: Energy Efficiency | H31: Member States are required to achieve cumulative end-use energy savings from 2021 to 2030, equivalent to new annual savings of at least 0.8% of final energy consumption in 2021-2023, at least 1.3% in 2024-2025, 1.5% in 2026-2027 and 1.9% in 2028-2030. Directive (EU) 2023/1791 | I31: + | J31: #1FA139 | K31: 1 | L31: The implementation of TA4.20 could reinforce the achievement of TA2.41 by increasing the share of renewable energy in the energy mix, thus contributing to the reduction of energy consumption and the increase of the share of renewable energy. | M31: this is true only if the produced GREEN H2 is used in a way that the final enrgy consumption are reduced (e.g. in a fuel cell in a car) the LLM is often confusing RES and EE reletionship | N31: Castellazzi Luca | O31: 8
A32: TA4.33 | B32: TA4 - Sustainable and smart mobility | C32: Energy Efficiency | D32: Member States shall ensure that at least one installation providing shore-side electricity supply to inland waterway vessels is deployed at all TEN-T core inland waterway ports by 1 January 2025, at least one installation providing shore-side electricity supply to inland waterway vessels is deployed at all TEN-T comprehensive inland waterway ports by 1 January 2030. Regulation (EU) 2023/1804 | E32: TA2.22 | F32: TA2 - Clean, affordable and secure energy | G32: Energy Efficiency | H32: Member States shall collectively ensure a reduction of energy consumption of at least 11.7% in 2030 compared to the projections of the 2020 EU Reference Scenario | I32: + | J32: #1FA139 | K32: 2 | L32: The implementation of TA4.33 could enable the achievement of TA2.22 by reducing energy consumption in the inland waterway sector, thus allowing for a greater share of renewable energy in the energy mix. | N32: Castellazzi Luca | O32: 8
A33: TA4.10 | B33: TA4 - Sustainable and smart mobility | C33: Energy Efficiency | D33: EU fisheries are encouraged to continue the positive trend, as observed for the period 2009-2019, towards reducing fuel intensity by reducing the fossil-fuel consumption per kg of landed product for at least an additional 15% for the period 2019-2030. Energy Transition of the EU Fisheries and Aquaculture sector | E33: TA2.23 | F33: TA2 - Clean, affordable and secure energy | G33: Energy Efficiency | H33: Member States shall make efforts to collectively contribute to the indicative Union primary energy consumption target amounting to no more than 992.5 Mtoe in 2030 | I33: + | J33: #1FA139 | K33: 2 | L33: The implementation of TA4.10 could support the achievement of TA2.23 by reducing energy consumption in the fisheries sector, thus allowing for a greater share of renewable energy in the energy mix. | N33: Castellazzi Luca | O33: 8
A34: TA2.17 | B34: TA2 - Clean, affordable and secure energy | C34: Energy Infrastructure | D34: A target of 15% electricity interconnection for 2030 | E34: TA4.33 | F34: TA4 - Sustainable and smart mobility | G34: Energy Efficiency | H34: Member States shall ensure that at least one installation providing shore-side electricity supply to inland waterway vessels is deployed at all TEN-T core inland waterway ports by 1 January 2025, at least one installation providing shore-side electricity supply to inland waterway vessels is deployed at all TEN-T comprehensive inland waterway ports by 1 January 2030. Regulation (EU) 2023/1804 | I34: + | J34: #1FA139 | K34: 1 | L34: The implementation of TA2.17, which aims to achieve a target of 15% electricity interconnection, may have a positive impact on TA4.33, which targets the deployment of shore-side electricity supply to inland waterway vessels. By increasing electricity interconnection, TA2.17 can support the achievement of TA4.33. | N34: Castellazzi Luca | O34: 8
A35: TA3.24 | B35: TA3 - Industrial strategy for a clean and circular economy | C35: Waste Reduction - Food Waste | D35: Reduce the generation of food waste in processing and manufacturing by 10% in comparison to the amount generated in 2020 | E35: TA2.41 | F35: TA2 - Clean, affordable and secure energy | G35: Energy Efficiency | H35: Member States are required to achieve cumulative end-use energy savings from 2021 to 2030, equivalent to new annual savings of at least 0.8% of final energy consumption in 2021-2023, at least 1.3% in 2024-2025, 1.5% in 2026-2027 and 1.9% in 2028-2030 Directive (EU) 2023/1791 | I35: + | J35: #1FA139 | K35: 2 | L35: The implementation of TA3.24 could support TA2.41 by reducing food waste, which could lead to increased energy savings. | N35: Castellazzi Luca | O35: 8
A36: TA3.3 | B36: TA3 - Industrial strategy for a clean and circular economy | C36: Circularity/Recycling | D36: Double EU‚Äö√Ñ√¥s circular material use rate in the coming decade | E36: TA2.41 | F36: TA2 - Clean, affordable and secure energy | G36: Energy Efficiency | H36: Member States are required to achieve cumulative end-use energy savings from 2021 to 2030, equivalent to new annual savings of at least 0.8% of final energy consumption in 2021-2023, at least 1.3% in 2024-2025, 1.5% in 2026-2027 and 1.9% in 2028-2030. Directive (EU) 2023/1791 | I36: + | J36: #1FA139 | K36: 2 | L36: The implementation of TA3.3 could reinforce TA2.41 by promoting energy efficiency and reducing energy consumption, which in turn could lead to increased energy savings and a higher share of renewable energy in the energy mix. | N36: Castellazzi Luca | O36: 8
A37: TA3.52 | B37: TA3 - Industrial strategy for a clean and circular economy | C37: Circularity/Recycling - Plastic & Packaging | D37: At least 20% of the carbon used in the chemical and plastic products should be from sustainable non-fossil sources by 2030, in full consideration of the EU's biodiversity and circular economy objectives and of the upcoming policy framework for bio-based, biodegradable and compostable plastics Communication on Sustainable Carbon Cycles | E37: TA2.41 | F37: TA2 - Clean, affordable and secure energy | G37: Energy Efficiency | H37: Member States are required to achieve cumulative end-use energy savings from 2021 to 2030, equivalent to new annual savings of at least 0.8% of final energy consumption in 2021-2023, at least 1.3% in 2024-2025, 1.5% in 2026-2027 and 1.9% in 2028-2030 Directive (EU) 2023/1791 | I37: + | J37: #1FA139 | K37: 1 | L37: The implementation of TA3.52 could support TA2.41 by promoting the use of sustainable non-fossil carbon sources, which could lead to increased energy savings. | N37: Castellazzi Luca | O37: 8
A38: TA4.1 | B38: TA4 - Sustainable and smart mobility | C38: Biofuels | D38: Achieve an annual production of sustainable biomethane of 35 billion cubic meters by 2030 | E38: TA2.41 | F38: TA2 - Clean, affordable and secure energy | G38: Energy Efficiency | H38: Member States are required to achieve cumulative end-use energy savings from 2021 to 2030, equivalent to new annual savings of at least 0.8% of final energy consumption in 2021-2023, at least 1.3% in 2024-2025, 1.5% in 2026-2027 and 1.9% in 2028-2030. Directive (EU) 2023/1791 | I38: + | J38: #1FA139 | K38: 1 | L38: The implementation of TA4.1 could reinforce the achievement of TA2.41 by increasing the share of renewable energy in the energy mix, thus contributing to the reduction of energy consumption. | M38: this is true only if the production of the biomethane consumes less than the production of the substituted fuel | N38: Castellazzi Luca | O38: 8
A39: TA5.27 | B39: TA5 - Greening the Common Agricultural Policy - Farm to Fork Strategy | C39: Food quality - Healthy Food | D39: Food messaging: Provide food information and labelling to empower consumers to make informed, healthy and sustainable food choices. Strengthen educational messages on the importance of healthy nutrition, sustainable food production and consumption, and reducing food waste | E39: TA4.10 | F39: TA4 - Sustainable and smart mobility | G39: Energy Efficiency | H39: EU fisheries are encouraged to continue the positive trend, as observed for the period 2009-2019, towards reducing fuel intensity by reducing the fossil-fuel consumption per kg of landed product for at least an additional 15% for the period 2019-2030. Energy Transition of the EU Fisheries and Aquaculture sector | I39: + | J39: #1FA139 | K39: 2 | L39: The implementation of TA5.27 could support the achievement of TA4.10 by promoting sustainable food systems and reducing food waste, increasing the use of renewable energy in fisheries and aquaculture. | N39: Castellazzi Luca | O39: 8
A40: TA6.33 | B40: TA6 - Preserving and protecting biodiversity | C40: Biodiversity Protection & Conservation | D40: Terrestrial, coastal and freshwater ecosystems. Member States shall put in place the restoration measures for the terrestrial, coastal and freshwater habitats of the species listed in Annexes II, IV and V | E40: TA2.23 | F40: TA2 - Clean, affordable and secure energy | G40: Energy Efficiency | H40: Member States shall make efforts to collectively contribute to the indicative Union primary energy consumption target amounting to no more than 992.5 Mtoe in 2030 | I40: + | J40: #1FA139 | K40: 2 | L40: The restoration of ecosystems can lead to the reduction of energy consumption, as restored ecosystems can provide ecosystem services, such as carbon sequestration, which can reduce the need for energy-intensive practices. | N40: Castellazzi Luca | O40: 8
A41: TA6.1 | B41: TA6 - Preserving and protecting biodiversity | C41: Biodiversity Protection & Conservation | D41: 1.a Legally protect a minimum of 30% of the EU land area | E41: TA1.8 | F41: TA1 - Climate ambition | G41: Energy Efficiency | H41: Reach energy neutrality in the wastewater treatment sector by 2045. | I41: + | J41: #1FA139 | K41: 1 | L41: The protection of land areas can contribute to the achievement of energy neutrality in the wastewater treatment sector by promoting sustainable land use practices and preserving ecosystem services, which are essential for reducing energy consumption and GHG emissions. | N41: Castellazzi Luca | O41: 8
A42: TA2.26 | B42: TA2 - Clean, affordable and secure energy | C42: Energy Efficiency - Buildings | D42: At least double the annual energy renovation rate of residential and non-residential buildings by 2030 | E42: TA1.3 | F42: TA1 - Climate ambition | G42: GHG Reduction | H42: Reduce by at least 55% net GHG emissions compared to 1990 levels, by 2030 | I42: + | J42: #1FA139 | K42: 3 | L42: The implementation of TA2.26 will aid in the achievement of TA1.3 by increasing the energy renovation rate of buildings. | M42: ok | N42: Delia Delgado | O42: 8
A43: TA2.33 | B43: TA2 - Clean, affordable and secure energy | C43: Energy Efficiency - Buildings | D43: The national measures will have to ensure that at least 55% of the decrease of the average primary energy use is achieved through the renovation of the worst-performing buildings | E43: TA1.3 | F43: TA1 - Climate ambition | G43: GHG Reduction | H43: Reduce by at least 55% net GHG emissions compared to 1990 levels, by 2030 | I43: + | J43: #1FA139 | K43: 3 | L43: The implementation of TA2.33 will aid in the achievement of TA1.3 by increasing the renovation of worst-performing buildings. | M43: ok | N43: Delia Delgado | O43: 8
A44: TA2.4 | B44: TA2 - Clean, affordable and secure energy | C44: Energy Efficiency - Buildings | D44: Double the current deployment rate of individual heat pumps, resulting in a cumulative 10 million units by 2027 and 30 million units by 2030 | E44: TA1.3 | F44: TA1 - Climate ambition | G44: GHG Reduction | H44: Reduce by at least 55% net GHG emissions compared to 1990 levels, by 2030 | I44: + | J44: #1FA139 | K44: 2 | L44: The implementation of TA2.4 will aid in the achievement of TA1.3 by increasing the deployment of heat pumps. | M44: ok | N44: Delia Delgado | O44: 8
A45: TA2.26 | B45: TA2 - Clean, affordable and secure energy | C45: Energy Efficiency - Buildings | D45: At least double the annual energy renovation rate of residential and non-residential buildings by 2030 | E45: TA5.11 | F45: TA5 - Greening the Common Agricultural Policy - Farm to Fork Strategy | G45: Biodiversity Protection & Conservation | H45: Biodiversity conservation and restoration of natural resources: Protect the environment and restore natural resources. Preserve biodiversity and reduce biodiversity loss. | I45: + | J45: #1FA139 | K45: 2 | L45: The increase in the annual energy renovation rate of residential and non-residential buildings, as per TA2.26, can positively impact TA5.11 by promoting sustainable building practices, reducing energy consumption, and supporting biodiversity conservation. | M45: ok | N45: Delia Delgado | O45: 8
A46: TA2.33 | B46: TA2 - Clean, affordable and secure energy | C46: Energy Efficiency - Buildings | D46: The national measures will have to ensure that at least 55% of the decrease of the average primary energy use is achieved through the renovation of the worst-performing buildings | E46: TA5.11 | F46: TA5 - Greening the Common Agricultural Policy - Farm to Fork Strategy | G46: Biodiversity Protection & Conservation | H46: Biodiversity conservation and restoration of natural resources: Protect the environment and restore natural resources. Preserve biodiversity and reduce biodiversity loss. | I46: + | J46: #1FA139 | K46: 2 | L46: The focus on renovating the worst-performing buildings, as mentioned in TA2.33, can reinforce the goals of TA5.11 by promoting sustainable practices, reducing energy consumption, and supporting biodiversity conservation. | M46: ok | N46: Delia Delgado | O46: 8
A47: TA2.4 | B47: TA2 - Clean, affordable and secure energy | C47: Energy Efficiency - Buildings | D47: Double the current deployment rate of individual heat pumps, resulting in a cumulative 10 million units by 2027 and 30 million units by 2030 | E47: TA5.11 | F47: TA5 - Greening the Common Agricultural Policy - Farm to Fork Strategy | G47: Biodiversity Protection & Conservation | H47: Biodiversity conservation and restoration of natural resources: Protect the environment and restore natural resources. Preserve biodiversity and reduce biodiversity loss. | I47: + | J47: #1FA139 | K47: 2 | L47: The deployment of heat pumps, as stated in TA2.4, can positively impact TA5.11 by promoting sustainable energy production, reducing greenhouse gas emissions, and supporting biodiversity conservation. | M47: ok | N47: Delia Delgado | O47: 8
A48: TA2.26 | B48: TA2 - Clean, affordable and secure energy | C48: Energy Efficiency - Buildings | D48: At least double the annual energy renovation rate of residential and non-residential buildings by 2030 | E48: TA7.15 | F48: TA7 - Towards a zero-pollution ambition for a toxic free environment | G48: Improve Soils Health | H48: Having all soils in healthy condition by 2050 | I48: + | J48: #1FA139 | K48: 2 | L48: The improvement of building energy efficiency will help to minimize the environmental impacts of building activities, making it more feasible to achieve the soil health targets. | M48: ok | N48: Delia Delgado | O48: 8
A49: TA2.28 | B49: TA2 - Clean, affordable and secure energy | C49: Energy Efficiency - Buildings | D49: Reduce buildings‚Äô energy consumption for heating and cooling by 18% compared to 2015 levels by 2030 | E49: TA7.10 | F49: TA7 - Towards a zero-pollution ambition for a toxic free environment | G49: Improve Water Quality | H49: Improve water quality by reducing waste, plastic litter at sea (by 50%) | I49: + | J49: #1FA139 | K49: 2 | L49: The reduction of energy consumption will help to minimize the environmental impacts of building activities, making it more feasible to achieve the water quality targets. | M49: ok | N49: Delia Delgado | O49: 8
A50: TA2.4 | B50: TA2 - Clean, affordable and secure energy | C50: Energy Efficiency - Buildings | D50: Double the current deployment rate of individual heat pumps, resulting in a cumulative 10 million units by 2027 and 30 million units by 2030 | E50: TA7.16 | F50: TA7 - Towards a zero-pollution ambition for a toxic free environment | G50: Improve Water Quality | H50: By means of an updated and harmonised list of pollutants affecting surface and groundwater, updated existing quality standards, new monitoring requirements, improved and more accessible data, and a more flexible framework for addressing pollutants of emerging concerns | I50: + | J50: #1FA139 | K50: 2 | L50: The increase of renewable energy sources will help to minimize the environmental impacts of energy production, making it more feasible to achieve the water quality targets. | M50: ok | N50: Delia Delgado | O50: 8
A51: TA2.24 | B51: TA2 - Clean, affordable and secure energy | C51: Energy Efficiency - Buildings | D51: Each Member State shall ensure that at least 3% of the total floor area of heated and/or cooled buildings is renovated each year to be transformed into at least nearly zero-energy buildings | E51: TA1.3 | F51: TA1 - Climate ambition | G51: GHG Reduction | H51: Reduce by at least 55% net GHG emissions compared to 1990 levels, by 2030 | I51: + | J51: #1FA139 | K51: 2 | L51: The implementation of TA2.24 may enable the achievement of TA1.3, as renovating buildings may not be sufficient to achieve the GHG emissions reduction target. | M51: ok | N51: Delia Delgado | O51: 8
A52: TA2.25 | B52: TA2 - Clean, affordable and secure energy | C52: Energy Efficiency - Buildings | D52: Reduce buildings final energy consumption by 14% | E52: TA1.3 | F52: TA1 - Climate ambition | G52: GHG Reduction | H52: Reduce by at least 55% net GHG emissions compared to 1990 levels, by 2030 | I52: + | J52: #1FA139 | K52: 2 | L52: The implementation of TA2.25 may enable the achievement of TA1.3, as reducing final energy consumption in buildings may not be sufficient to achieve the GHG emissions reduction target. | N52: Delia Delgado | O52: 8
A53: TA2.26 | B53: TA2 - Clean, affordable and secure energy | C53: Energy Efficiency - Buildings | D53: At least double the annual energy renovation rate of residential and non-residential buildings by 2030 | E53: TA1.3 | F53: TA1 - Climate ambition | G53: GHG Reduction | H53: Reduce by at least 55% net GHG emissions compared to 1990 levels, by 2030 | I53: + | J53: #1FA139 | K53: 3 | L53: The implementation of TA2.26 may enable the achievement of TA1.3, as increasing the energy renovation rate may not be sufficient to achieve the GHG emissions reduction target. | N53: Delia Delgado | O53: 8
A54: TA2.28 | B54: TA2 - Clean, affordable and secure energy | C54: Energy Efficiency - Buildings | D54: Reduce buildings energy consumption for heating and cooling by 18% compared to 2015 levels by 2030 | E54: TA1.3 | F54: TA1 - Climate ambition | G54: GHG Reduction | H54: Reduce by at least 55% net GHG emissions compared to 1990 levels, by 2030 | I54: + | J54: #1FA139 | K54: 2 | L54: The implementation of TA2.28 may enable the achievement of TA1.3, as reducing energy consumption for heating and cooling may not be sufficient to achieve the GHG emissions reduction target. | N54: Delia Delgado | O54: 8
A55: TA2.29 | B55: TA2 - Clean, affordable and secure energy | C55: Energy Efficiency - Buildings | D55: Member states will have to renovate 16% of worst-performing non-residential buildings by 2030 | E55: TA1.3 | F55: TA1 - Climate ambition | G55: GHG Reduction | H55: Reduce by at least 55% net GHG emissions compared to 1990 levels, by 2030 | I55: + | J55: #1FA139 | K55: 3 | L55: The implementation of TA2.29 will contribute to the achievement of TA1.3 by increasing the renovation of non-residential buildings. | M55: ok | N55: Delia Delgado | O55: 8
A56: TA2.33 | B56: TA2 - Clean, affordable and secure energy | C56: Energy Efficiency - Buildings | D56: The national measures will have to ensure that at least 55% of the decrease of the average primary energy use is achieved through the renovation of the worst-performing buildings | E56: TA1.3 | F56: TA1 - Climate ambition | G56: GHG Reduction | H56: Reduce by at least 55% net GHG emissions compared to 1990 levels, by 2030 | I56: + | J56: #1FA139 | K56: 2 | L56: The implementation of TA2.33 may enable the achievement of TA1.3, as renovating the worst-performing buildings may not be sufficient to achieve the GHG emissions reduction target. | M56: ok | N56: Delia Delgado | O56: 8
A57: TA2.34 | B57: TA2 - Clean, affordable and secure energy | C57: Energy Efficiency - Buildings | D57: Member States shall ensure that the average primary energy use of the entire residential building stock decreases by at least 16% compared to 2020 by 2030 | E57: TA1.3 | F57: TA1 - Climate ambition | G57: GHG Reduction | H57: Reduce by at least 55% net GHG emissions compared to 1990 levels, by 2030 | I57: + | J57: #1FA139 | K57: 2 | L57: The implementation of TA2.34 will contribute to the achievement of TA1.3 by reducing the primary energy use of residential buildings. | M57: ok | N57: Delia Delgado | O57: 8
A58: TA2.4 | B58: TA2 - Clean, affordable and secure energy | C58: Energy Efficiency - Buildings | D58: Double the current deployment rate of individual heat pumps, resulting in a cumulative 10 million units by 2027 and 30 million units by 2030 | E58: TA1.3 | F58: TA1 - Climate ambition | G58: GHG Reduction | H58: Reduce by at least 55% net GHG emissions compared to 1990 levels, by 2030 | I58: + | J58: #1FA139 | K58: 1 | L58: The implementation of TA2.4 may enable the achievement of TA1.3, as increasing the deployment rate of heat pumps may not be sufficient to achieve the GHG emissions reduction target. | M58: ok | N58: Delia Delgado | O58: 8
A59: TA2.25 | B59: TA2 - Clean, affordable and secure energy | C59: Energy Efficiency - Buildings | D59: Reduce buildings final energy consumption by 14% | E59: TA5.11 | F59: TA5 - Greening the Common Agricultural Policy - Farm to Fork Strategy | G59: Biodiversity Protection & Conservation | H59: Biodiversity conservation and restoration of natural resources: Protect the environment and restore natural resources. Preserve biodiversity and reduce biodiversity loss. | I59: + | J59: #1FA139 | K59: 1 | L59: The reduction of buildings' final energy consumption, as outlined in TA2.25, can contribute to the conservation of biodiversity, as stated in TA5.11, by minimizing the environmental footprint of buildings and promoting sustainable construction practices. | M59: ok | N59: Delia Delgado | O59: 8
A60: TA2.24 | B60: TA2 - Clean, affordable and secure energy | C60: Energy Efficiency - Buildings | D60: Each Member State shall ensure that at least 3% of the total floor area of heated and/or cooled buildings is renovated each year to be transformed into at least nearly zero-energy buildings | E60: TA7.5 | F60: TA7 - Towards a zero-pollution ambition for a toxic free environment | G60: Improve Water Quality | H60: The revised Urban Wastewater Treatment Directive (UWWTD) extends the scope of the 1991 UWWTD | I60: + | J60: #1FA139 | K60: 1 | L60: The reduction of wastewater emissions will help to minimize the environmental impacts of urban activities, making it more feasible to achieve the wastewater treatment targets. | M60: ok | N60: Delia Delgado | O60: 8
A61: TA1.15 | B61: TA1 - Climate ambition | C61: GHG Reduction - Buildings | D61: Reduce buildings greenhouse gas emissions by 60%, by 2030 | E61: TA2.25 | F61: TA2 - Clean, affordable and secure energy | G61: Energy Efficiency - Buildings | H61: Reduce buildings final energy consumption by 14% | I61: + | J61: #1FA139 | K61: 2 | L61: The implementation of TA1.15 will likely enable the achievement of TA2.25, as reducing greenhouse gas emissions from buildings will require energy-efficient buildings, which in turn will contribute to reducing final energy consumption. | M61: ok | N61: Delia Delgado | O61: 8
A62: TA1.8 | B62: TA1 - Climate ambition | C62: Energy Efficiency | D62: Reach energy neutrality in the wastewater treatment sector by 2045 | E62: TA2.25 | F62: TA2 - Clean, affordable and secure energy | G62: Energy Efficiency - Buildings | H62: Reduce buildings final energy consumption by 14% | I62: + | J62: #1FA139 | K62: 1 | L62: The implementation of TA1.8 will likely enable the achievement of TA2.25, as energy neutrality in the wastewater treatment sector will require energy-efficient buildings and renewable energy sources, which in turn will contribute to reducing final energy consumption in buildings. | M62: ok | N62: Delia Delgado | O62: 8
A63: TA4.1 | B63: TA4 - Sustainable and smart mobility | C63: Biofuels | D63: Achieve an annual production of sustainable biomethane of 35 billion cubic meters by 2030 | E63: TA2.41 | F63: TA2 - Clean, affordable and secure energy | G63: Energy Efficiency | H63: Member States are required to achieve cumulative end-use energy savings from 2021 to 2030, equivalent to new annual savings of at least 0.8% of final energy consumption in 2021-2023, at least 1.3% in 2024-2025, 1.5% in 2026-2027 and 1.9% in 2028-2030. Directive (EU) 2023/1791 | I63: + | J63: #1FA139 | K63: 2 | L63: The implementation of TA4.1 could reinforce the achievement of TA2.41 by increasing the share of renewable energy in the energy mix, thus contributing to the reduction of energy consumption. | M63: boh, cannot comment | N63: Sarah Mubareka | O63: 1
A64: TA4.7 | B64: TA4 - Sustainable and smart mobility | C64: Biofuels | D64: Each Member State shall set an obligation on fuel suppliers to ensure that: (B) the combined share of advanced biofuels and biogas produced from the feedstock listed in Part A of Annex IX and of renewable fuels of non-biological origin in the energy supplied to the transport sector is at least 1% in 2025 and 5.5% in 2030, of which a share of at least 1 percentage point is from renewable fuels of non-biological origin in 2030. Directive (EU) 2023/2413 | E64: TA2.9 | F64: TA2 - Clean, affordable and secure energy | G64: Renewable Energy | H64: Member States shall collectively ensure that the share of energy from renewable sources in the Union gross final consumption of energy in 2030 is at least 42.5% | I64: + | J64: #1FA139 | K64: 2 | L64: The implementation of TA4.7 could support the achievement of TA2.9 by promoting the use of renewable fuels in the transport sector, thus contributing to the increase of the share of renewable energy in the energy mix. | M64: maybe | N64: Sarah Mubareka | O64: 1
A65: TA4.5 | B65: TA4 - Sustainable and smart mobility | C65: Biofuels | D65: Aviation fuel suppliers shall also ensure that Sustainable Aviation Fuel (SAF) made available to aircraft operators at each Union airport will be at least 2% from 2025, 6% from 2030, 20% from 2035, 34% from 2040, 42% from 2045 and 70% from 2050. Regulation (EU) 2023/2405 | E65: TA2.37 | F65: TA2 - Clean, affordable and secure energy | G65: Renewable Energy | H65: By 2030, the share of renewable energy in the electricity mix should double to 55-60% | I65: + | J65: #1FA139 | K65: 2 | L65: The implementation of TA4.5 could support the achievement of TA2.37 by promoting the use of Sustainable Aviation Fuels, thus contributing to the increase of the share of renewable energy in the electricity mix. | M65: assuming the aviation fuels are used to generate electricity I guess this is possible | N65: Sarah Mubareka | O65: 1
A66: TA4.7 | B66: TA4 - Sustainable and smart mobility | C66: Biofuels | D66: Each Member State shall set an obligation on fuel suppliers to ensure that: (B) the combined share of advanced biofuels and biogas produced from the feedstock listed in Part A of Annex IX and of renewable fuels of non-biological origin in the energy supplied to the transport sector is at least 1% in 2025 and 5.5% in 2030, of which a share of at least 1 percentage point is from renewable fuels of non-biological origin in 2030. Directive (EU) 2023/2413 | E66: TA5.14 | F66: TA5 - Greening the Common Agricultural Policy - Farm to Fork Strategy | G66: Circularity/Recycling | H66: Circular economy: Scale-up and promote sustainable and socially responsible production methods and circular business models in food processing and retail. | I66: + | J66: #1FA139 | K66: 2 | L66: The implementation of advanced biofuels and renewable fuels of non-biological origin can support the development of a circular economy in the food sector by promoting the use of waste and residual biomass as feedstock for the production of biofuels. | M66: comment in row 3 applies however if this is also a source of income there would be a positive synergy | N66: Sarah Mubareka | O66: 1
... A94: TA5.20 | B94: TA5 - Greening the Common Agricultural Policy - Farm to Fork Strategy | C94: Competitive Agriculture | D94: Trade: Foster the competitiveness of the EU supply sector. | E94: TA4.5 | F94: TA4 - Sustainable and smart mobility | G94: Biofuels | H94: Aviation fuel suppliers shall also ensure that Sustainable Aviation Fuel (SAF) made available to aircraft operators at each Union airport will be at least 2% from 2025, 6% from 2030, 20% from 2035, 34% from 2040, 42% from 2045 and 70% from 2050. Regulation (EU) 2023/2405 | I94: + | J94: #1FA139 | K94: 2 | L94: The implementation of TA5.20 could reinforce the achievement of TA4.5 by promoting the competitiveness of the EU supply sector and increasing the demand for sustainable aviation fuels. | M94: not evaluated | N94: Sarah Mubareka | O94: 1
A95: TA6.3 | B95: TA6 - Preserving and protecting biodiversity | C95: Biodiversity Protection & Conservation | D95: 2.a Strictly protect at least a third of the EU'S protected areas | E95: TA4.5 | F95: TA4 - Sustainable and smart mobility | G95: Biofuels | H95: Aviation fuel suppliers shall also ensure that Sustainable Aviation Fuel (SAF) made available to aircraft operators at each Union airport will be at least 2% from 2025, 6% from 2030, 20% from 2035, 34% from 2040, 42% from 2045 and 70% from 2050. Regulation (EU) 2023/2405 | I95: - | J95: #DA2620 | K95: 2 | L95: The strict protection of EU protected areas might limit the areas available for SAF production, thus counteracting the aviation fuel target. | N95: Sarah Mubareka | O95: 1
A96: TA4.31 | B96: TA4 - Sustainable and smart mobility | C96: Hydrogen Distribution | D96: Member States shall ensure that, by 31 December 2030, publicly accessible hydrogen refuelling stations with a total capacity of at least 1 tonne per day, and equipped with at least a 700 bar dispenser, are deployed at least every 200 km along the TEN-T (Trans-European Transport Network) core network Regulation (EU) 2023/1804 | E96: TA6.42 | F96: TA6 - Preserving and protecting biodiversity | G96: Marine Ecosystem Restoration | H96: ecosystems. Member States shall put in place the restoration measures that are necessary to re-establish the habitat types of groups 1-6 listed in Annex II | I96: + | J96: #1FA139 | K96: 2 | L96: The deployment of hydrogen refuelling stations along the TEN-T core network could support the restoration of ecosystems, potentially contributing to the re-establishment of habitat types. | M96: I agree, the replacement of fossil fuel refueling stations could contribute positively | N96: Eveline Weider | O96: NA
A97: TA4.30 | B97: TA4 - Sustainable and smart mobility | C97: Hydrogen Distribution | D97: Member States shall ensure that, by 31 December 2030, at least one publicly accessible hydrogen refuelling station is deployed in each urban node. Regulation (EU) 2023/1804 | E97: TA2.38 | F97: TA2 - Clean, affordable and secure energy | G97: Renewable Energy - Ocean/Offshore | H97: Cumulative EU offshore goals of installed capacity: 60 GW by 2030 and 300 GW by 2050 | I97: + | J97: #1FA139 | K97: 1 | L97: The implementation of TA4.30 could support the achievement of TA2.38 by increasing the share of renewable energy in the energy mix, thus allowing for a greater share of renewable energy in the offshore sector. | M97: Not very direct, but yes | N97: Eveline Weider | O97: NA
A98: TA4.31 | B98: TA4 - Sustainable and smart mobility | C98: Hydrogen Distribution | D98: Member States shall ensure that, by 31 December 2030, publicly accessible hydrogen refuelling stations with a total capacity of at least 1 tonne per day, and equipped with at least a 700 bar dispenser, are deployed at least every 200 km along the TEN-T (Trans-European Transport Network) core network Regulation (EU) 2023/1804 | E98: TA2.39 | F98: TA2 - Clean, affordable and secure energy | G98: Renewable Energy - Ocean/Offshore | H98: The strategy sets targets for an installed capacity of at least 1 GW of ocean energy by 2030 and 40 GW by 2050 | I98: + | J98: #1FA139 | K98: 1 | L98: The implementation of TA4.31 could enable the achievement of TA2.39 by increasing the share of renewable energy in the energy mix, thus allowing for a greater share of renewable energy in the ocean energy sector. | M98: Not very direct, but yes | N98: Eveline Weider | O98: NA
A99: TA1.3 | B99: TA1 - Climate ambition | C99: GHG Reduction | D99: Reduce by at least 55% net GHG emissions compared to 1990 levels, by 2030 | E99: TA4.30 | F99: TA4 - Sustainable and smart mobility | G99: Hydrogen Distribution | H99: Member States shall ensure that, by 31 December 2030, at least one publicly accessible hydrogen refuelling station is deployed in each urban node. Regulation (EU) 2023/1804 | I99: + | J99: #1FA139 | K99: 2 | L99: The reduction of GHG emissions will create a favorable environment for the deployment of hydrogen refuelling stations, which can help achieve the EU's climate goals. | M99: agreed | N99: Eveline Weider | O99: NA
A100: TA1.3 | B100: TA1 - Climate ambition | C100: GHG Reduction | D100: Reduce by at least 55% net GHG emissions compared to 1990 levels, by 2030 | E100: TA4.30 | F100: TA4 - Sustainable and smart mobility | G100: Hydrogen Distribution | H100: Member States shall ensure that, by 31 December 2030, at least one publicly accessible hydrogen refuelling station is deployed in each urban node. Regulation (EU) 2023/1804 | I100: + | J100: #1FA139 | K100: 1 | L100: The implementation of TA1.3 will enable the achievement of TA4.30, as reducing GHG emissions will lead to increased investment in low-carbon technologies, including hydrogen production and related infrastructure. | M100: agreed | N100: Eveline Weider | O100: NA
A101: TA1.3 | B101: TA1 - Climate ambition | C101: GHG Reduction | D101: Reduce by at least 55% net GHG emissions compared to 1990 levels, by 2030 | E101: TA4.31 | F101: TA4 - Sustainable and smart mobility | G101: Hydrogen Distribution | H101: Member States shall ensure that, by 31 December 2030, publicly accessible hydrogen refuelling stations with a total capacity of at least 1 tonne per day, and equipped with at least a 700 bar dispenser, are deployed at least every 200 km along the TEN-T (Trans-European Transport Network) core network Regulation (EU) 2023/1804 | I101: + | J101: #1FA139 | K101: 1 | L101: The implementation of TA1.3 will enable the achievement of TA4.31, as reducing GHG emissions will lead to increased investment in low-carbon technologies, including hydrogen production and related infrastructure. | M101: agreed | N101: Eveline Weider | O101: NA
A102: TA2.37 | B102: TA2 - Clean, affordable and secure energy | C102: Renewable Energy | D102: By 2030, the share of renewable energy in the electricity mix should double to 55-60% | E102: TA4.30 | F102: TA4 - Sustainable and smart mobility | G102: Hydrogen Distribution | H102: Member States shall ensure that, by 31 December 2030, at least one publicly accessible hydrogen refuelling station is deployed in each urban node. Regulation (EU) 2023/1804 | I102: + | J102: #1FA139 | K102: 1 | L102: The implementation of TA2.37, which aims to increase the share of renewable energy in the electricity mix, may have a positive impact on TA4.30, which targets the deployment of publicly accessible hydrogen refuelling stations. By increasing the share of renewable energy, TA2.37 can support the achievement of TA4.30. | M102: agreed | N102: Eveline Weider | O102: NA
A103: TA2.3 | B103: TA2 - Clean, affordable and secure energy | C103: Renewable Energy - Hydrogen Production | D103: Member States shall ensure that the contribution of renewable fuels of non-biological origin used for final energy and non-energy purposes shall be at least 42% of the hydrogen used for final energy and non-energy purposes in industry by 2030 | E103: TA4.31 | F103: TA4 - Sustainable and smart mobility | G103: Hydrogen Distribution | H103: Member States shall ensure that, by 31 December 2030, publicly accessible hydrogen refuelling stations with a total capacity of at least 1 tonne per day, and equipped with at least a 700 bar dispenser, are deployed at least every 200 km along the TEN-T (Trans-European Transport Network) core network Regulation (EU) 2023/1804 | I103: + | J103: #1FA139 | K103: 1 | L103: The implementation of TA2.3, which aims to ensure the contribution of renewable fuels of non-biological origin, may have a positive impact on TA4.31, which targets the deployment of publicly accessible hydrogen refuelling stations with a total capacity of at least 1 tonne per day. By promoting the use of renewable fuels, TA2.3 can support the achievement of TA4.31. | M103: agreed | N103: Eveline Weider | O103: NA
A104: TA5.18 | B104: TA5 - Greening the Common Agricultural Policy - Farm to Fork Strategy | C104: Competitive Agriculture | D104: Market power and business structure: Improve agricultural rules that strengthen the position of farmers (e.g. producers of products with geographical indications), their cooperatives and producer organisations in the food supply chain. | E104: TA4.30 | F104: TA4 - Sustainable and smart mobility | G104: Hydrogen Distribution | H104: Member States shall ensure that, by 31 December 2030, at least one publicly accessible hydrogen refuelling station is deployed in each urban node. Regulation (EU) 2023/1804 | I104: - | J104: #DA2620 | K104: 1 | L104: The implementation of TA5.18 could constrain the achievement of TA4.30 by limiting the options for energy access and increasing the costs for farmers and food producers. | M104: Agreed | N104: Eveline Weider | O104: NA
A105: TA6.11 | B105: TA6 - Preserving and protecting biodiversity | C105: Terrestrial Ecosystems Restoration - Forests | D105: 9. Three billion trees are planted in the EU, in full respect of ecological principles | E105: TA4.30 | F105: TA4 - Sustainable and smart mobility | G105: Hydrogen Distribution | H105: Member States shall ensure that, by 31 December 2030, at least one publicly accessible hydrogen refuelling station is deployed in each urban node. Regulation (EU) 2023/1804 | I105: - | J105: #DA2620 | K105: 1 | L105: The planting of trees might compete with the deployment of hydrogen refuelling stations, as it could require large areas of land. | M105: Agreed | N105: Eveline Weider | O105: NA
A106: TA6.33 | B106: TA6 - Preserving and protecting biodiversity | C106: Biodiversity Protection & Conservation | D106: Terrestrial, coastal and freshwater ecosystems. Member States shall put in place the restoration measures for the terrestrial, coastal and freshwater habitats of the species listed in Annexes II, IV and V | E106: TA4.30 | F106: TA4 - Sustainable and smart mobility | G106: Hydrogen Distribution | H106: Member States shall ensure that, by 31 December 2030, at least one publicly accessible hydrogen refuelling station is deployed in each urban node. Regulation (EU) 2023/1804 | I106: - | J106: #DA2620 | K106: 1 | L106: The restoration of ecosystems might compete with the deployment of hydrogen refuelling stations, as it could require large areas of land. | M106: Agreed | N106: Eveline Weider | O106: NA
A107: TA1.10 | B107: TA1 - Climate ambition | C107: GHG Reduction - Buildings | D107: ETS2. Contribution of the buildings and road transport sectors of 43% emission reductions by 2030 compared to 2005 | E107: TA2.9 | F107: TA2 - Clean, affordable and secure energy | G107: Renewable Energy | H107: Member States shall collectively ensure that the share of energy from renewable sources in the Union gross final consumption of energy in 2030 is at least 42.5% | I107: + | J107: #1FA139 | K107: 2 | L107: The implementation of TA1.10 will likely reinforce the achievement of TA2.9, as reducing emissions from the ETS2 sector will require an increase in renewable energy sources, which in turn will contribute to reaching the 42.5% target. | M107: ok | N107: Downing Paul | O107: 9
A108: TA1.10 | B108: TA1 - Climate ambition | C108: GHG Reduction - Buildings | D108: ETS2. Contribution of the buildings and road transport sectors of 43% emission reductions by 2030 compared to 2005 | E108: TA4.1 | F108: TA4 - Sustainable and smart mobility | G108: Biofuels | H108: Achieve an annual production of sustainable biomethane of 35 billion cubic meters by 2030 | I108: + | J108: #1FA139 | K108: 1 | L108: The ETS2 will drive the growth of the sustainable biomethane market by creating a carbon pricing mechanism that incentivizes the production of low-carbon energy sources. | M108: change weight to 1 | N108: Downing Paul | O108: 9
A109: TA1.10 | B109: TA1 - Climate ambition | C109: GHG Reduction - Buildings | D109: ETS2. Contribution of the buildings and road transport sectors of 43% emission reductions by 2030 compared to 2005 | E109: TA4.7 | F109: TA4 - Sustainable and smart mobility | G109: Biofuels | H109: Each Member State shall set an obligation on fuel suppliers to ensure that: (B) the combined share of advanced biofuels and biogas produced from the feedstock listed in Part A of Annex IX and of renewable fuels of non-biological origin in the energy supplied to the transport sector is at least 1% in 2025 and 5.5% in 2030, of which a share of at least 1 percentage point is from renewable fuels of non-biological origin in 2030. Directive (EU) 2023/2413 | I109: + | J109: #1FA139 | K109: 1 | L109: The ETS2 will drive the growth of the sustainable biomethane market by creating a framework for the reduction of GHG emissions in the transport sector. | M109: change weight to 1 | N109: Downing Paul | O109: 9
A110: TA1.15 | B110: TA1 - Climate ambition | C110: GHG Reduction - Buildings | D110: Reduce buildings greenhouse gas emissions by 60%, by 2030 | E110: TA2.25 | F110: TA2 - Clean, affordable and secure energy | G110: Energy Efficiency - Buildings | H110: Reduce buildings final energy consumption by 14% | I110: + | J110: #1FA139 | K110: 3 | L110: The implementation of TA1.15 will likely enable the achievement of TA2.25, as reducing greenhouse gas emissions from buildings will require energy-efficient buildings, which in turn will contribute to reducing final energy consumption. | M110: change weight to 3 | N110: Downing Paul | O110: 9
A111: TA1.10 | B111: TA1 - Climate ambition | C111: GHG Reduction - Buildings | D111: ETS2. Contribution of the buildings and road transport sectors of 43% emission reductions by 2030 compared to 2005 | E111: TA7.14 | F111: TA7 - Towards a zero-pollution ambition for a toxic free environment | G111: Noise Reduction | H111: Reduce the share of people chronically disturbed by transport noise by 30%, by 2030 | I111: + | J111: #1FA139 | K111: 1 | L111: The reduction of emissions from the transport sector will contribute to reducing transport noise and improving air quality. | M111: correct, but the justification is wrong, the direction of the link is the opposite, better insulated homes will reduce noise exposure | N111: Downing Paul | O111: 9
A112: TA3.9 | B112: TA3 - Industrial strategy for a clean and circular economy | C112: Critical Raw Materials - Extraction & Import | D112: By 2030, Union processing capacity, including for all intermediate processing steps, should be able of producing at least 40% of the Union annual consumption of strategic raw materials | E112: TA1.10 | F112: TA1 - Climate ambition | G112: GHG Reduction - Buildings | H112: ETS2. Contribution of the buildings and road transport sectors of 43% emission reductions by 2030 compared to 2005 | I112: + | J112: #1FA139 | K112: 1 | L112: The implementation of TA3.9 will aid TA1.10 by increasing the processing capacity, which will reduce waste and increase the recycling rate, contributing to the reduction of GHG emissions. | M112: ok | N112: Downing Paul | O112: 9
A113: TA5.30 | B113: TA5 - Greening the Common Agricultural Policy - Farm to Fork Strategy | C113: Food affordability | D113: Food affordability: Ensure affordability to sufficient, nutritious and sustainable food | E113: TA1.10 | F113: TA1 - Climate ambition | G113: GHG Reduction - Buildings | H113: ETS2. Contribution of the buildings and road transport sectors of 43% emission reductions by 2030 compared to 2005 | I113: - | J113: #DA2620 | K113: 1 | L113: The ETS2 may have a negative impact on food affordability, as it may increase production costs, which could affect the price of food. | M113: ok | N113: Downing Paul | O113: 9
A114: TA4.15 | B114: TA4 - Sustainable and smart mobility | C114: GHG Reduction - Transports | D114: The average CO2 emissions of the Union fleet of new heavy-duty motor vehicles [...], off-road vehicles and off-road special purpose vehicles shall be reduced by the following percentages compared to the average CO2 emissions of the reporting period of the year 2019: (a) 15% for vehicle sub-groups 4-UD, 4-RD, 4-LH, 5-RD, 5-LH, 9-RD, 9-LH, 10-RD and 10-LH for the reporting periods of the years 2025 to 2029, (b) 45% for all vehicle sub-groups other than vocational vehicles for the reporting periods of the years 2030 to 2034, (c) 65% for all vehicle sub-groups for the reporting periods of the years 2035 to 2039, (d) 90% for all vehicle sub-groups for the reporting periods of the year 2040 onwards Regulation (EU) 2024/1610 | E114: TA2.3 | F114: TA2 - Clean, affordable and secure energy | G114: Renewable Energy - Hydrogen Production | H114: Member States shall ensure that the contribution of renewable fuels of non-biological origin used for final energy and non-energy purposes shall be at least 42% of the hydrogen used for final energy and non-energy purposes in industry by 2030 | I114: + | J114: #1FA139 | K114: 2 | L114: The implementation of TA4.15 could reinforce the achievement of TA2.3 by reducing CO2 emissions from heavy-duty vehicles, thus allowing for a greater share of renewable energy in the industry sector. | M114: ok | N114: Downing Paul | O114: 9
A115: TA4.3 | B115: TA4 - Sustainable and smart mobility | C115: GHG Reduction - Transports | D115: The yearly average GHG intensity of the energy used on board by a ship during a reporting period shall be reduced, compared to the reference value (91.16 gCO2e/MJ) by: 2% from 1 January 2025, 6% from 1 January 2030, 14.5% from 1 January 2035, 31% from 1 January 2040, 62% from 1 January 2045, 80% from 1 January 2050. Regulation (EU) 2023/1805 | E115: TA2.1 | F115: TA2 - Clean, affordable and secure energy | G115: Renewable Energy - Hydrogen Production | H115: REPowerEU sets a target of 10 million tonnes of domestic renewable hydrogen production and 10 million tonnes of renewable hydrogen imports by 2030 | I115: + | J115: #1FA139 | K115: 2 | L115: The implementation of TA4.3 could support the achievement of TA2.1 by reducing GHG emissions from shipping, thus allowing for a greater share of renewable energy in the energy mix. | M115: ok | N115: Downing Paul | O115: 9
A116: TA4.9 | B116: TA4 - Sustainable and smart mobility | C116: GHG Reduction - Transports | D116: Cut the emissions of transport sector by 90% by 2050 relative to 1990. Sustainable and Smart Mobility Strategy | E116: TA7.9 | F116: TA7 - Towards a zero-pollution ambition for a toxic free environment | G116: Improve Air Quality | H116: Improve air quality to reduce the number of premature deaths caused by air pollution by 55% by 2030 | I116: + | J116: #1FA139 | K116: 2 | L116: The reduction of emissions from the transport sector can contribute to improved air quality, thus reducing the number of premature deaths caused by air pollution. | M116: ok | N116: Downing Paul | O116: 9
A117: TA4.9 | B117: TA4 - Sustainable and smart mobility | C117: GHG Reduction - Transports | D117: Cut the emissions of transport sector by 90% by 2050 relative to 1990. Sustainable and Smart Mobility Strategy | E117: TA7.14 | F117: TA7 - Towards a zero-pollution ambition for a toxic free environment | G117: Noise Reduction | H117: Reduce the share of people chronically disturbed by transport noise by 30%, by 2030 | I117: + | J117: #1FA139 | K117: 2 | L117: The reduction of transport noise can be supported by the development of low-carbon fuels and the reduction of emissions from the transport sector, thus creating a more favorable environment for the reduction of noise pollution. | M117: impact type and weight are ok. But the justification is incorrect. Reducing emissions in transport will happen via electric vehicles, which are quiter than internal combustion engines | N117: Downing Paul | O117: 9
A118: TA4.3 | B118: TA4 - Sustainable and smart mobility | C118: GHG Reduction - Transports | D118: The yearly average GHG intensity of the energy used on board by a ship during a reporting period shall be reduced, compared to the reference value (91.16 gCO2e/MJ) by: 2% from 1 January 2025, 6% from 1 January 2030, 14.5% from 1 January 2035, 31% from 1 January 2040, 62% from 1 January 2045, 80% from 1 January 2050. Regulation (EU) 2023/1805 | E118: TA3.30 | F118: TA3 - Industrial strategy for a clean and circular economy | G118: Circularity/Recycling - Municipal Waste | H118: Each Member State shall reduce the packaging waste generated per capita, as compared to the packaging waste generated per capita in 2018 as reported to the Commission in accordance with Decision 2005/270/EC by 5% by 2030, 10% by 2035, 15% by 2040 Proposal on packaging and packaging waste | I118: + | J118: #1FA139 | K118: 1 | L118: The reduction of GHG emissions from ships can lead to a decrease in the demand for packaging waste, supporting the reduction targets for packaging waste. | M118: impact type and weight are ok. But the justification is in the other direction, less packing means less transport needed, so the reduced packagind faciliates emission reductions in transport. | N118: Downing Paul | O118: 9
... A136: TA6.2 | B136: TA6 - Preserving and protecting biodiversity | C136: Biodiversity Protection & Conservation - Fisheries | D136: 1.b Legally protect a minimum of 30% of the EU's sea area | E136: TA2.38 | F136: TA2 - Clean, affordable and secure energy | G136: Renewable Energy - Ocean/Offshore | H136: Cumulative EU offshore goals of installed capacity: 60 GW by 2030 and 300 GW by 2050 | I136: + | J136: #1FA139 | K136: 1 | L136: The protection of sea areas can lead to the development of offshore renewable energy sources, such as wind farms, which can increase the share of renewable energy in the energy mix. | M136: I would say its -1 since with enhanced sea protection, the available space for Offshore wind is reduced (should be the same for TA2.39) | N136: Evdokia Tapoglou | O136: 6
A137: TA6.50 | B137: TA6 - Preserving and protecting biodiversity | C137: Improve Soils Health | D137: Reach no net land take | E137: TA1.3 | F137: TA1 - Climate ambition | G137: GHG Reduction | H137: Reduce by at least 55% net GHG emissions compared to 1990 levels, by 2030 | I137: + | J137: #1FA139 | K137: 2 | L137: The implementation of no net land take will contribute to the reduction of GHG emissions, as it will promote sustainable land use practices, which are essential for achieving the EU's climate ambition. | N137: Alberto Orgiazzi | O137: NA
A138: TA2.5 | B138: TA2 - Clean, affordable and secure energy | C138: Renewable Energy - Solar | D138: Bring online over 320 GW of solar photovoltaic by 2025 and almost 600 GW by 2030 | E138: TA1.3 | F138: TA1 - Climate ambition | G138: GHG Reduction | H138: Reduce by at least 55% net GHG emissions compared to 1990 levels, by 2030 | I138: + | J138: #1FA139 | K138: 3 | L138: The implementation of TA2.5 will aid in the achievement of TA1.3 by increasing the solar photovoltaic capacity. | M138: Would put this at 3 since without solar, the GHG target is not practially possible in the EU (I stress the need for technologies that can be deployed at 100 GW scale in a short time period) | N138: Taylor Nigel | O138: NA
A139: TA2.5 | B139: TA2 - Clean, affordable and secure energy | C139: Renewable Energy - Solar | D139: Bring online over 320 GW of solar photovoltaic by 2025 and almost 600 GW by 2030 | E139: TA5.11 | F139: TA5 - Greening the Common Agricultural Policy - Farm to Fork Strategy | G139: Biodiversity Protection & Conservation | H139: Biodiversity conservation and restoration of natural resources: Protect the environment and restore natural resources. Preserve biodiversity and reduce biodiversity loss. | I139: + | J139: #1FA139 | K139: 1 | L139: The deployment of solar photovoltaic, as mentioned in TA2.5, can reinforce the objectives of TA5.11 by promoting sustainable energy production, reducing energy consumption, and supporting biodiversity conservation. | M139: OK (somewhere between 1 asnd 2) | N139: Taylor Nigel | O139: NA
A140: TA2.7 | B140: TA2 - Clean, affordable and secure energy | C140: Renewable Energy - Solar | D140: Over this decade, the EU will need to install, on average, approximately 45 GW per year of PV to reach the share of 45% of energy coming from renewables | E140: TA1.3 | F140: TA1 - Climate ambition | G140: GHG Reduction | H140: Reduce by at least 55% net GHG emissions compared to 1990 levels, by 2030 | I140: + | J140: #1FA139 | K140: 2 | L140: The implementation of TA2.7 may enable the achievement of TA1.3, as increasing PV installation may not be sufficient to achieve the GHG emissions reduction target. | M140: 2 as above, without PV reaching the GHG targets is practically not possible | N140: Taylor Nigel | O140: NA
A141: TA2.7 | B141: TA2 - Clean, affordable and secure energy | C141: Renewable Energy - Solar | D141: Over this decade, the EU will need to install, on average, approximately 45 GW per year of PV to reach the share of 45% of energy coming from renewables | E141: TA1.3 | F141: TA1 - Climate ambition | G141: GHG Reduction | H141: Reduce by at least 55% net GHG emissions compared to 1990 levels, by 2030 | I141: + | J141: #1FA139 | K141: 2 | L141: The implementation of TA2.7 will contribute to the achievement of TA1.3 by increasing the solar photovoltaic capacity. | M141: 2 as above, without PV reaching the GHG targets is practically not possible | N141: Taylor Nigel | O141: NA
A142: TA2.5 | B142: TA2 - Clean, affordable and secure energy | C142: Renewable Energy - Solar | D142: Bring online over 320 GW of solar photovoltaic by 2025 and almost 600 GW by 2030 | E142: TA4.11 | F142: TA4 - Sustainable and smart mobility | G142: Transport Logistics | H142: Reduce the average door-to-door cost of combined transport operations by at least 10% within 7 years Proposal for a Directive to support framework for intermodal transport of goods | I142: + | J142: #1FA139 | K142: 1 | L142: The implementation of TA2.5, which aims to bring online solar photovoltaic capacity, may have a positive impact on TA4.11, which targets the reduction of the average door-to-door cost of combined transport operations. By increasing the availability of renewable energy, TA2.5 can support the achievement of TA4.11. | M142: OK | N142: Taylor Nigel | O142: NA
A143: TA2.7 | B143: TA2 - Clean, affordable and secure energy | C143: Renewable Energy - Solar | D143: Over this decade, the EU will need to install, on average, approximately 45 GW per year of PV to reach the share of 45% of energy coming from renewables | E143: TA4.27 | F143: TA4 - Sustainable and smart mobility | G143: Energy Infrastructure | H143: Member States shall ensure that, by 31 December 2030 (with intermediate 2025 and 2027 targets), along the TEN-T core road network, publicly accessible recharging pools dedicated to heavy-duty electric vehicles are deployed in each direction of travel with a maximum distance of 60 km between them [...]. Along the TEN-T comprehensive road network, recharging pools dedicated to heavy-duty electric vehicles are deployed in each direction of travel with a maximum distance of 100 km between them and each recharging pool offers a power output of at least 1.500 kW and includes at least one recharging point with an individual power output of at least 350 kW. Regulation (EU) 2023/1804 | I143: + | J143: #1FA139 | K143: 1 | L143: The implementation of TA2.7, which aims to install solar photovoltaic capacity, may have a positive impact on TA4.27, which targets the deployment of publicly accessible recharging points for heavy-duty electric vehicles. By increasing the availability of renewable energy, TA2.7 can support the achievement of TA4.27. | M143: no comment | N143: Taylor Nigel | O143: NA
A144: TA2.7 | B144: TA2 - Clean, affordable and secure energy | C144: Renewable Energy - Solar | D144: Over this decade, the EU will need to install, on average, approximately 45 GW per year of PV to reach the share of 45% of energy coming from renewables | E144: TA5.11 | F144: TA5 - Greening the Common Agricultural Policy - Farm to Fork Strategy | G144: Biodiversity Protection & Conservation | H144: Biodiversity conservation and restoration of natural resources: Protect the environment and restore natural resources. Preserve biodiversity and reduce biodiversity loss. | I144: + | J144: #1FA139 | K144: 1 | L144: The installation of photovoltaic capacity, as stated in TA2.7, can contribute to the conservation of biodiversity, as outlined in TA5.11, by promoting sustainable energy production and reducing energy consumption. | M144: same as row 4? | N144: Taylor Nigel | O144: NA
...

Sheet all_targets
A1: thematic - area | B1: sub_theme | C1: sub_theme_color | D1: target_code | E1: is_source_target | F1: is_impact_target | G1: target_content | H1: target_assessment | I1: policy_document
A2: TA1 - Climate ambition | B2: GHG Reduction - Buildings | C2: #DDEBF7 | D2: TA1.10 | E2: =ISNUMBER(MATCH(D2,data!A:A)) -> TRUE | F2: =ISNUMBER(MATCH(D2,data!E:E)) -> TRUE | G2: ETS2. Contribution of the buildings and road transport sectors of 43% emission reductions by 2030 compared to 2005 | H2: The ETS2 is a new EU-wide cap-and-trade economic instrument that covers the CO2 emissions from the combustion of fuels in road transport, buildings, and other sectors (mainly smaller industries), excluding agriculture. Monitoring starts in 2025, with cap and trade applying from 2027. As such, it overlaps significantly with the ESR in terms of sectors covered, but important differences are that a) it is implemented at the EU level, rather than through Member State-specific policies, and b) it does not cover non-CO2 emissions, many of which are from the hard-to- tackle agricultural sector. Between 2005 and 2022, the emissions covered by the ETS 2 fell by 16% according to own estimates of the JRC. However, since the ETS2 instrument is newly implemented and official reporting by Member States is not yet available, the progress cannot currently be evaluated. | I2: Amending Directive 2003/87/EC establishing a system for greenhouse gas emission allowance trading within the Union, Decision (EU) 2015/1814 concerning the establishment and operation of a market stability reserve for the Union greenhouse gas emission trading system
B3: GHG Reduction - Transports | C3: #DDEBF7 | D3: TA1.10 | E3: =ISNUMBER(MATCH(D3,data!A:A)) -> TRUE | F3: =ISNUMBER(MATCH(D3,data!E:E)) -> TRUE | G3: ETS2. Contribution of the buildings and road transport sectors of 43% emission reductions by 2030 compared to 2005 | H3: The ETS2 is a new EU-wide cap-and-trade economic instrument that covers the CO2 emissions from the combustion of fuels in road transport, buildings, and other sectors (mainly smaller industries), excluding agriculture. Monitoring starts in 2025, with cap and trade applying from 2027. As such, it overlaps significantly with the ESR in terms of sectors covered, but important differences are that a) it is implemented at the EU level, rather than through Member State-specific policies, and b) it does not cover non-CO2 emissions, many of which are from the hard-to- tackle agricultural sector. Between 2005 and 2022, the emissions covered by the ETS 2 fell by 16% according to own estimates of the JRC. However, since the ETS2 instrument is newly implemented and official reporting by Member States is not yet available, the progress cannot currently be evaluated. | I3: Amending Directive 2003/87/EC establishing a system for greenhouse gas emission allowance trading within the Union, Decision (EU) 2015/1814 concerning the establishment and operation of a market stability reserve for the Union greenhouse gas emission trading system
B4: GHG Reduction | C4: #DDEBF7 | D4: TA1.11 | E4: =ISNUMBER(MATCH(D4,data!A:A)) -> TRUE | F4: =ISNUMBER(MATCH(D4,data!E:E)) -> TRUE | G4: ESR. Increased national targets in line with an EU- wide reduction of 40% in the ESR sectors compared to 2005 | H4: The current (2022) reduction is 17% relative to 2005, far from the 40% reduction target set for 2030. Between 2013 and 2020, Member States met or overa- chieved their ESR obligations- with the largest reductions in the buildings and small industry sectors. Emissions are expected to continue decreasing in the com- ing decade due to –among others- source control legislation, such as improved building standards, building renovations, CO2 standards for road vehicles and EU policies on phasing down hydrofluorocarbons (HFC) and other fluorinated gases. Progress in the transport and building sectors faces different challenges. While transport emissions are regulated by EU-wide CO2 emission standards for vehicles (which have a relatively fast turnover rate), renovating the building stock is a more challenging effort, primarily driven by Member States' policies. Therefore, Member States' projections for building emissions significantly lag behind the expected cost-effective rate of reduction [31]. Overall, EU emissions in the sectors covered by the ESR, according to 2023 Member States projections, are expected to fall by 27-32% (with existing and ad- ditional measures, respectively) by 2030 compared to 2005, i.e. 8 -13 percentage points below the 40% target for 2030, with only 6 Member States projected to (over-) achieve their targets [22]. Absolute emissions in the agriculture sector have stagnated since 2010, while agricultural aggregate output has increased, decreasing emission intensity of EU agricultural products by 13%. Concerning emission reductions, current Member States' projections under the Governance Regulation foresee 2030 emissions with existing measures to be 373 MtCO2e (or -3% compared to 2021) and 359 MtCO2e (or -7 %) with additional measures. The 2030 ‘MIX (55 Euro/t CO2e)’ scenario, used to assess the Fit for 55 targets corresponds to a -7 % decline in the agricultural sector by 2030 compared to 2021, aligning with the Member States ‘with additional measures’ scenario. The current (2023-2027) CAP aims to contribute to climate mitigation, with Member State strategies outlined in their Strategic Plans. Estimates of the CAP 2023-2027 impact on emissions require detailed information on the implementation and effectiveness of farming practices from the CAP instruments, which are currently being evaluated. | I4: Amending Regulation (EU) 2018/842 on binding annual greenhouse gas emission reductions by Member States from 2021 to 2030 contributing to climate action to meet commitments under the Paris Agreement, and Regulation (EU) 2018/1999
B5: GHG Removal | C5: #DDEBF7 | D5: TA1.12 | E5: =ISNUMBER(MATCH(D5,data!A:A)) -> TRUE | F5: =ISNUMBER(MATCH(D5,data!E:E)) -> TRUE | G5: Achieve an EU net greenhouse gas removal of 310 million tonnes CO2 equivalent per year for the land use, land use change and forestry (LULUCF) sector, by 2030 | H5: The revised LULUCF regulation sets a target of removing 310 MtCO2e by 2030. The long-term EU forest sink is developing away from this target and jeopard- ising the fulfilment of the overall LULUCF sector target for 2030. Furthermore, natural disturbances are expected to increase with ongoing climate change, with potentially a further reduction of the carbon sink, making the situation even more difficult. In 2020, the gap between the reported LULUCF emissions in 2016-2018 and the target of -310 MtCO2e for 2030 was -42 MtCO2e for the EU. 2024 shows that this gap has now widened: instead of -42 MtCO2e, the EU needs to improve its LULUCF sink by -80 MtCO2e between 2022 and 2030 to meet the targets. The LULUCF targets will be difficult to achieve unless substantial changes in forest manage- ment are implemented very soon. | I5: Amending Regulations (EU) 2018/841 as regards the scope, simplifying the compliance rules, setting out the targets of the Member States for 2030 and committing to the collective achievement of climate neutrality by 2035 in the land use, forestry and agriculture sector, and (EU) 2018/1999 as regards improvement in monitoring, reporting, tracking of progress and review
B6: GHG Reduction | C6: #DDEBF7 | D6: TA1.13 | E6: =ISNUMBER(MATCH(D6,data!A:A)) -> TRUE | F6: =ISNUMBER(MATCH(D6,data!E:E)) -> TRUE | G6: No debit rule. For the period from 2021 to 2025, each Member State shall ensure that greenhouse gas emissions from the sector do not exceed greenhouse gas removals | H6: Assessing the distance to the target is difficult. Comparing purely the GHG re- porting from countries for 2021 and 2022, to the accounting benchmark of -229 MtCO2e determined by the delegated act, it looks like the EU is slightly exceeding the accounting benchmark. However, the recalculations of the inventories have increased the net sink historical time series reported by the Member States, and those recalculations will be considered in the accounting. Given the sharp decline of the forest sink driven by increasing harvest levels and natural disturbances, it is likely that the EU will face an overall accounting debit (i.e. not reaching the target) than a credit in the LULUCF sector as a whole. The reporting for years 2026-2029 will be done in GHG inventories during 2028- 2031. | I6: Amending Regulations (EU) 2018/841 as regards the scope, simplifying the compliance rules, setting out the targets of the Member States for 2030 and committing to the collective achievement of climate neutrality by 2035 in the land use, forestry and agriculture sector, and (EU) 2018/1999 as regards improvement in monitoring, reporting, tracking of progress and review
B7: GHG Reduction - Buildings | C7: #DDEBF7 | D7: TA1.15 | E7: =ISNUMBER(MATCH(D7,data!A:A)) -> TRUE | F7: =ISNUMBER(MATCH(D7,data!E:E)) -> TRUE | G7: Reduce buildings‚Äô greenhouse gas emissions by 60%, by 2030 | H7: In 2015 buildings direct GHG emissions were 541 MtCO2e, therefore the target value for 2030 is 216 MtCO2e. European Climate Neutrality Observatory data shows past progress of 5 MtCO2e between 2016 and 2021. To meet the target, the required annual change between 2021 and 2030 needs to be 7.5 times faster than the past rate of progress. Overall, buildings are responsible for about 40% of the EU’s total energy consumption, and for 36% of its greenhouse gas emissions from energy (including indirect emissions). Buildings related emissions belonging to fossil fuelled district heating, electric heating and electricity use of heat pumps are covered by EU ETS, while the rest is covered by the ESR. | I7: A Renovation Wave for Europe - greening our buildings, creating jobs, improving lives
B8: Climate Resilience | C8: #DDEBF7 | D8: TA1.3 | E8: =ISNUMBER(MATCH(D8,data!A:A)) -> TRUE | F8: =ISNUMBER(MATCH(D8,data!E:E)) -> TRUE | G8: Reduce by at least 55% net GHG emissions compared to 1990 levels, by 2030 | H8: The at least 55% economy-wide net reduction objective is enshrined in the Climate Law as an overall ambition at the EU level. Specific legislation covering different sectors translates this into sectoral ambition levels which cumulatively achieve the -55% target. This corresponds to greenhouse gas reductions of 62% in the existing ETS compared to 2005, a 40% reduction in ESR, (this is now complemented by 42% reduction target compared to 2005 in the newly established ETS2). With the aim of ensuring strong emissions reduction in other sectors, the overall contribution of the LULUCF sector to EU’s economy-wide target of − 55% by 2030 is limited to a maximum of − 225 MtCO2e/year. Achieving the LULUCF sector target of -310 MtCO2e in 2030 will elevate the total EU GHG emission reduction to approximately 57% compared to 1990. The total net EU greenhouse gases emissions, including LULUCF, were reduced by 32.5% between 1990 and 2022 [21]. GHG emission reductions need to double in the current decade compared to the previous decades (see charts in the annexes). According to the Member States’ own projections reported in 2023 under Article 18 of the Governance of the Energy Union Regulation, total EU emissions are expected to fall in 2030 by about 50% below the 1990 level when factoring in additional measures. This falls short of the at least 55% objective, but the Member States projections do not accurately capture the evolution driven by EU-wide instruments such as the ETS. Reaching the -55 % objective further depends on delivery of ESR, which is not fully on track, as well as the related functioning of ETS2. In addition, the -55% objective assumes that the LULUCF sink is at least -225 MtCO2e. The agreed LULUCF commitment of -310 MtCO2e could even achieve -57%. However, the current development of the LULUCF sink is opposite to the targets, including natural disturbances that are expected to further increase with the ongoing climate change [27], [28]. If this negative development continues, the risk of not reaching the sink of –225 MtCO2 cannot be ruled out. On the other hand, the implementation of the complete Fit for 55 legislative package is expected to reduce EU net greenhouse gas emissions by 57% by 2030, putting EU on track to exceed 2030 targets [29]. On the way to climate neutrality by 2050, the Commission adopted a Communica- tion [23] in February 2024 that launches the process of setting the 2040 climate target for the EU, in compliance with Art. 4.3 of the Climate Law. While 2040 targets are not yet set, it is clear that much of the transition to 2050 has to be realised by 2040. Based on the recommended emission reductions of 90-95 % by 2040 compared to 1990, of the European Scientific Advisory Board on Climate Change advised, the Commission has recommended a net 90% GHG reduction target for 2040. Both 2040 and 2050 targets require a much deeper transformation of the energy system, through large scale deployment of climate-neutral technologies that require high investment efforts with some technologies not yet deployed at market scale. While some of the current instruments will keep delivering reductions well beyond 2030 (notably the EU ETS but also CO2 standards for vehicles, ReFuelEU Aviation, FuelEU Maritime and the Fluorinated gas (F-gas) Regulation), there will be a need to review, update and complete the legislative framework for the post-2030 period. This will include topics such as carbon capture, industrial carbon removals, and overall and sector specific emission reduction trajectories. In addition, larger emis- sion reductions in difficult-to-abate sectors like agriculture will be needed, along with a larger role for carbon removals, including utilising land as a carbon sink. | I8: Establishing the framework for achieving climate neutrality and amending regulations (EC) No 401/2009 and (EU) 2018/1999 ("European Climate Law")
B9: GHG Reduction | C9: #DDEBF7 | D9: TA1.3 | E9: =ISNUMBER(MATCH(D9,data!A:A)) -> TRUE | F9: =ISNUMBER(MATCH(D9,data!E:E)) -> TRUE | G9: Reduce by at least 55% net GHG emissions compared to 1990 levels, by 2030 | H9: The at least 55% economy-wide net reduction objective is enshrined in the Climate Law as an overall ambition at the EU level. Specific legislation covering different sectors translates this into sectoral ambition levels which cumulatively achieve the -55% target. This corresponds to greenhouse gas reductions of 62% in the existing ETS compared to 2005, a 40% reduction in ESR, (this is now complemented by 42% reduction target compared to 2005 in the newly established ETS2). With the aim of ensuring strong emissions reduction in other sectors, the overall contribution of the LULUCF sector to EU’s economy-wide target of − 55% by 2030 is limited to a maximum of − 225 MtCO2e/year. Achieving the LULUCF sector target of -310 MtCO2e in 2030 will elevate the total EU GHG emission reduction to approximately 57% compared to 1990. The total net EU greenhouse gases emissions, including LULUCF, were reduced by 32.5% between 1990 and 2022 [21]. GHG emission reductions need to double in the current decade compared to the previous decades (see charts in the annexes). According to the Member States’ own projections reported in 2023 under Article 18 of the Governance of the Energy Union Regulation, total EU emissions are expected to fall in 2030 by about 50% below the 1990 level when factoring in additional measures. This falls short of the at least 55% objective, but the Member States projections do not accurately capture the evolution driven by EU-wide instruments such as the ETS. Reaching the -55 % objective further depends on delivery of ESR, which is not fully on track, as well as the related functioning of ETS2. In addition, the -55% objective assumes that the LULUCF sink is at least -225 MtCO2e. The agreed LULUCF commitment of -310 MtCO2e could even achieve -57%. However, the current development of the LULUCF sink is opposite to the targets, including natural disturbances that are expected to further increase with the ongoing climate change [27], [28]. If this negative development continues, the risk of not reaching the sink of –225 MtCO2 cannot be ruled out. On the other hand, the implementation of the complete Fit for 55 legislative package is expected to reduce EU net greenhouse gas emissions by 57% by 2030, putting EU on track to exceed 2030 targets [29]. On the way to climate neutrality by 2050, the Commission adopted a Communica- tion [23] in February 2024 that launches the process of setting the 2040 climate target for the EU, in compliance with Art. 4.3 of the Climate Law. While 2040 targets are not yet set, it is clear that much of the transition to 2050 has to be realised by 2040. Based on the recommended emission reductions of 90-95 % by 2040 compared to 1990, of the European Scientific Advisory Board on Climate Change advised, the Commission has recommended a net 90% GHG reduction target for 2040. Both 2040 and 2050 targets require a much deeper transformation of the energy system, through large scale deployment of climate-neutral technologies that require high investment efforts with some technologies not yet deployed at market scale. While some of the current instruments will keep delivering reductions well beyond 2030 (notably the EU ETS but also CO2 standards for vehicles, ReFuelEU Aviation, FuelEU Maritime and the Fluorinated gas (F-gas) Regulation), there will be a need to review, update and complete the legislative framework for the post-2030 period. This will include topics such as carbon capture, industrial carbon removals, and overall and sector specific emission reduction trajectories. In addition, larger emis- sion reductions in difficult-to-abate sectors like agriculture will be needed, along with a larger role for carbon removals, including utilising land as a carbon sink. | I9: Establishing the framework for achieving climate neutrality and amending regulations (EC) No 401/2009 and (EU) 2018/1999 ("European Climate Law")
B10: GHG Reduction | C10: #DDEBF7 | D10: TA1.7 | E10: =ISNUMBER(MATCH(D10,data!A:A)) -> TRUE | F10: =ISNUMBER(MATCH(D10,data!E:E)) -> TRUE | G10: Reduce methane emissions by 35 to 37% compared to 2005 levels, by 2030 | H10: Methane emissions were 497.15 MtCO2e in 2005 and decreased to 394.37 MtCO2e in 2022, making a reduction of about 20.67%. However, acceleration is needed to reach at least a 35% reduction by 2030. The largest source of methane emissions in the EU is the agriculture sector, accounting for more than half of the total emissions, followed by the energy and waste sectors. Within agriculture, almost all methane emissions are from livestock: 80% of the total stems from enteric fermentation and 18% from manure man- agement. Furthermore, the energy sector showed the highest decline in emissions, primarily due to the mitigation of fugitive emissions from fuels, including emis- sions from the extraction of solid fuels and those associated with oil and natural gas production and distribution. Most methane emissions from the waste sector come from solid waste disposal. GHG Emissions | I10: On an EU Strategy to reduce methane emissions
B11: Methane | C11: #DDEBF7 | D11: TA1.7 | E11: =ISNUMBER(MATCH(D11,data!A:A)) -> TRUE | F11: =ISNUMBER(MATCH(D11,data!E:E)) -> TRUE | G11: Reduce methane emissions by 35 to 37% compared to 2005 levels, by 2030 | H11: Methane emissions were 497.15 MtCO2e in 2005 and decreased to 394.37 MtCO2e in 2022, making a reduction of about 20.67%. However, acceleration is needed to reach at least a 35% reduction by 2030. The largest source of methane emissions in the EU is the agriculture sector, accounting for more than half of the total emissions, followed by the energy and waste sectors. Within agriculture, almost all methane emissions are from livestock: 80% of the total stems from enteric fermentation and 18% from manure man- agement. Furthermore, the energy sector showed the highest decline in emissions, primarily due to the mitigation of fugitive emissions from fuels, including emis- sions from the extraction of solid fuels and those associated with oil and natural gas production and distribution. Most methane emissions from the waste sector come from solid waste disposal. GHG Emissions | I11: On an EU Strategy to reduce methane emissions
B12: Energy Efficiency | C12: #DDEBF7 | D12: TA1.8 | E12: =ISNUMBER(MATCH(D12,data!A:A)) -> TRUE | F12: =ISNUMBER(MATCH(D12,data!E:E)) -> TRUE | G12: Reach energy neutrality in the wastewater treatment sector by 2045. | H12: There is a considerable potential for reducing fossil fuel-based energy use and GHG emissions in wastewater treatment and market incentives are increasingly attractive for investments in this direction. Member states should be required to ensure that the total annual energy used by all urban wastewater treatment plants on their territory treating a load of 10 000 population equivalent1 and above does not exceed the production of energy from renewable sources. 1 A number expressing the ratio of the sum of the pollution load in wastewater to the individual pollution load in household sewage produced by one person at the same time | I12: Concerning urban wastewater treatment (recast)
B13: GHG Reduction | C13: #DDEBF7 | D13: TA1.9 | E13: =ISNUMBER(MATCH(D13,data!A:A)) -> TRUE | F13: =ISNUMBER(MATCH(D13,data!E:E)) -> TRUE | G13: EU ETS. The contribution of the sectors covered by the existing EU Emission trading System (EU ETS) with respect to the EU Climate ambition should be of -62% compared to 2005 | H13: The decreasing trajectory of the number of CO2 emission allowances is expected to lead to -62% less CO2 emission in 2030 compared to 2005 levels. EU ETS emissions fell by 47% between 2005 and 2022. The most important driver for the decrease in EU ETS emissions has been the power sector, due to a substantial in- crease in renewable electricity production (primarily wind and solar) at the expense of both coal and gas. The system covers the electricity sector, large industry, and since 2012, aviation (initially intra-European Economic Area, with an upcoming extension of scope). Since 1 January 2024, it has been expanded to include the maritime sector [30]. The 2023 greenhouse gas emission projections reported by the Member States to the EEA [15], [22] result in a reduction of ETS emissions of 55% to 59% (with existing measures – with additional measures projection) in the ETS sectors in 2030. While these projections are short of the 62% target, it is important to note that, the ETS being an EU-wide market-based (cap and trade) instrument, this objective is not directly addressed by Member States specific policies and cannot be consistently and comprehensively covered by the individual Member States GHG emission projections. Given that the ETS instrument is established and operational, and that the nec- essary technologies are both available and affordable, it is anticipated that the target can be achieved. | I13: Amending Directive 2003/87/EC establishing a system for greenhouse gas emission allowance trading within the Union, Decision (EU) 2015/1814 concerning the establishment and operation of a market stability reserve for the Union greenhouse gas emission trading system
A14: TA2 - Clean, affordable and secure energy | B14: Renewable Energy - Hydrogen Production | C14: #FFF2CC | D14: TA2.1 | E14: =ISNUMBER(MATCH(D14,data!A:A)) -> TRUE | F14: =ISNUMBER(MATCH(D14,data!E:E)) -> TRUE | G14: REPowerEU sets a target of 10 million tonnes of domestic renewable hydrogen production and 10 million tonnes of renewable hydrogen imports by 2030 | H14: European production capacity is not yet officially monitored, but there are estimates of production of around 23ktH2/year, which is very far away from the target of 10 MtH2/year. Imports are currently non-existent. | I14: REPowerEU Plan
B15: Renewable Energy | C15: #FFF2CC | D15: TA2.10 | E15: =ISNUMBER(MATCH(D15,data!A:A)) -> TRUE | F15: =ISNUMBER(MATCH(D15,data!E:E)) -> TRUE | G15: Member States shall set an indicative target for innovative renewable energy technology of at least 5% of newly installed renewable energy capacity by 2030 | H15: Innovative technologies are defined as those that improve in at least one way comparable state-of-the-art renewable energy technologies or make exploitable a largely untapped renewable energy resource, involving a clear degree of risk, in technological, market or financial terms, which is higher than the risk generally associated with comparable non-innovative technologies or activities. According to the Association of European Renewable Energy Research Centers (EUREC) [73], the EU’s industry is ready, in the right circumstances, to deploy innovative renewable energy technologies to a level likely to exceed 5%, including innovative technologies such as advanced photovoltaics, floating photovoltaics, concentrated solar power and solar thermal. | I15: amending Directive (EU) 2018/2001, Regulation (EU) 2018/1999 and Directive 98/70/EC as regards the promotion of energy from renewable sources, and repealing Council Directive (EU) 2015/652
B16: Renewable Energy | C16: #FFF2CC | D16: TA2.11 | E16: =ISNUMBER(MATCH(D16,data!A:A)) -> TRUE | F16: =ISNUMBER(MATCH(D16,data!E:E)) -> TRUE | G16: By 31 December 2025, each Member State shall agree to establish a framework for cooperation on joint projects with one or more other Member States for the production of renewable energy | H16: Joint projects allow for a cost-efficient deployment of renewable energy across Europe and contribute to market integration. Despite its potential, cooperation between Member States has been very limited, thus leading to suboptimal results in terms of efficiency in increasing renewable energy. There are a few projects under consideration and being planned, as well as some permitting and under construction. However, these are in localised areas across the EU and not homogeneously distributed between Member States. | I16: amending Directive (EU) 2018/2001, Regulation (EU) 2018/1999 and Directive 98/70/EC as regards the promotion of energy from renewable sources, and repealing Council Directive (EU) 2015/652
B17: Renewable Energy | C17: #FFF2CC | D17: TA2.13 | E17: =ISNUMBER(MATCH(D17,data!A:A)) -> TRUE | F17: =ISNUMBER(MATCH(D17,data!E:E)) -> TRUE | G17: The amount of renewable fuels and renewable electricity supplied to the transport sector leads to a: (i) share of renewable energy within the final consumption of energy in the transport sector of at least 29 % by 2030 | H17: The share of energy from renewable sources used in transport in the EU reached 9.6 % in 2022, up from 9.1% in 2021. Acceleration is needed to reach the 2030 target. Following a sharp 13.5% drop in transport related GHG emissions between 2019 and 2020, due to the COVID-19 pandemic, according to European Environ- ment Agency (EEA) data, they surged upwards (by 8.6%) between 2020 and 2021 from 720.2 to 782.1 Mt (million tonnes) and the EEA forecasts a further 2.7% increase for 2022, which would restore emission levels to above the 800-Mtonne threshold (803.2 Mt in 2022). CO2 emissions account for almost all transport related GHG emissions (98.9% in 2021) and far outstrip those of nitrous oxide (N2O) (0.9% in CO2 equivalent units) and methane (0.2% in CO2 equivalent units). | I17: amending Directive (EU) 2018/2001, Regulation (EU) 2018/1999 and Directive 98/70/EC as regards the promotion of energy from renewable sources, and repealing Council Directive (EU) 2015/652
B18: Renewable Energy - Heating & Cooling | C18: #FFF2CC | D18: TA2.14 | E18: =ISNUMBER(MATCH(D18,data!A:A)) -> TRUE | F18: =ISNUMBER(MATCH(D18,data!E:E)) -> TRUE | G18: Each Member State shall increase the share of renewable energy in the heating and cooling sector by at least 0.8 percentage points as an annual average calculated for the period 2021 to 2025 | H18: Energy for heating and cooling makes up around half of the EU’s total gross final energy consumption. The annual average increases would lead to a target of 32.48% share by 2030. In 2022, the share of energy from renewables in heating and cooling continued to rise, with the EU average standing at 24.8%, up 1.8 percentage points from 2021 (23.0%). However, the 2022 value is still below the expected annual average. In absolute terms, the gross final consumption of renewable energy for heating and cooling purposes in the EU has gradually increased over time, mostly due to the contribution of biomass and heat pumps. However, a major push is required to meet the 2030 target. Sweden led the way when it came to renewables in heating and cooling, with a 69.3% share, followed by Estonia (65.4%). Both countries use mostly biomass and heat pumps. They are followed by Latvia (61.0%), which relies mostly on biomass. | I18: amending Directive (EU) 2018/2001, Regulation (EU) 2018/1999 and Directive 98/70/EC as regards the promotion of energy from renewable sources, and repealing Council Directive (EU) 2015/652
B19: Renewable Energy | C19: #FFF2CC | D19: TA2.15 | E19: =ISNUMBER(MATCH(D19,data!A:A)) -> TRUE | F19: =ISNUMBER(MATCH(D19,data!E:E)) -> TRUE | G19: By 2022, achieve 18% of the total increase in the share of energy from renewable sources between that Member State‚Äôs binding 2020 national target, and its contribution to the 2030 target | H19: Two Member States (Malta and Sweden) have already reached their 2030 target. 18 Member States have achieved the 2022 target of 18%. However, in 2021, 10 Member States experienced a decline in their share respect their 2020 value. This occurred as well for seven Member States in 2022, nevertheless, two of them have still met their 2022 targets despite the decrease. The EU jointly has reached the 2022 sub-target. | I19: amending Directive (EU) 2018/2001, Regulation (EU) 2018/1999 and Directive 98/70/EC as regards the promotion of energy from renewable sources, and repealing Council Directive (EU) 2015/652
B20: Renewable Energy | C20: #FFF2CC | D20: TA2.16 | E20: =ISNUMBER(MATCH(D20,data!A:A)) -> TRUE | F20: =ISNUMBER(MATCH(D20,data!E:E)) -> TRUE | G20: Member States shall endeavour to increase the share of renewable sources in the amount of energy sources used for final energy and non-energy purposes in the industry sector by an indicative increase of at least 1.6 percentage points | H20: A 1.6 percentage point annual increase leads to a 26% share of renewables by 2030. The share of renewables in 2022 was 10.7%, an increase from 9.7% in 2020. In absolute values, this is an increase from 23.3 Mtoe in 2021 to 24.1 Mtoe in 2022 Acceleration is needed to reach the 2030 target. | I20: amending Directive (EU) 2018/2001, Regulation (EU) 2018/1999 and Directive 98/70/EC as regards the promotion of energy from renewable sources, and repealing Council Directive (EU) 2015/652
B21: Energy Infrastructure | C21: #FFF2CC | D21: TA2.17 | E21: =ISNUMBER(MATCH(D21,data!A:A)) -> TRUE | F21: =ISNUMBER(MATCH(D21,data!E:E)) -> TRUE | G21: A target of 15% electricity interconnection for 2030 | H21: In 2021, 16 countries reported being on track to reach that target by 2030, or had already reached the target, but more interconnections are needed in some regions. Specifically, eight Member States have already met or are exceeding the EU target. Others commit in their draft NECPs to develop interconnections with neighbouring countries by investing in new transmission capacities and interconnectors, espe- cially in regions that are historically dependent on a single supplier and now aim to improve diversification. Moreover, some Member States (e.g. EE, FI, IT and PT) plan to diversify their energy mix by carrying out joint hydrogen infrastructure projects [7]. Overall, Member States have made good efforts to increase cross-border capacity and the completion of various Projects of Common Interest should further improve the interconnectivity levels. Some Member States (CZ, IT, PT RO, SI, SE) are reporting delays in the completion of the projects in particular due to permitting issues. Still further efforts are required to meet the 2030 objectives, especially in terms of timely delivery of the planned cross-border projects [72]. | I21: amending Directive (EU) 2018/2001, Regulation (EU) 2018/1999 and Directive 98/70/EC as regards the promotion of energy from renewable sources, and repealing Council Directive (EU) 2015/652
B22: Renewable Energy - Heating & Cooling | C22: #FFF2CC | D22: TA2.18 | E22: =ISNUMBER(MATCH(D22,data!A:A)) -> TRUE | F22: =ISNUMBER(MATCH(D22,data!E:E)) -> TRUE | G22: Indicative target of at least a 49% share of energy from renewable sources in the building sector in the Union‚Äôs final energy consumption in buildings in 2030 | H22: No data available for buildings, only for the heating and cooling sector. From this data, the most reported fuels and technologies in 2021 per country are: biomass (21 countries), heat pumps (19), solar thermal systems (17), geothermal systems (12) and other decentralised renewable sources (8). | I22: amending Directive (EU) 2018/2001, Regulation (EU) 2018/1999 and Directive 98/70/EC as regards the promotion of energy from renewable sources, and repealing Council Directive (EU) 2015/652
B23: Renewable Energy | C23: #FFF2CC | D23: TA2.2 | E23: =ISNUMBER(MATCH(D23,data!A:A)) -> TRUE | F23: =ISNUMBER(MATCH(D23,data!E:E)) -> TRUE | G23: Set up at least one renewables-based energy community in every municipality with a population higher than 10.000 by 2025 | H23: For the 2010-2021 period, energy communities in the EU were still a niche in most national energy markets, with an estimated 9250 energy communities currently in operation across the EU and highly unbalanced distribution among Member States. More than half of these are located in Germany and almost 1000 are in the Netherlands. To date, however, a systematic and cross-country database on citizen-led initiatives and projects is lacking [74]. | I23: EU Solar Energy Strategy
B24: Energy Efficiency | C24: #FFF2CC | D24: TA2.21 | E24: =ISNUMBER(MATCH(D24,data!A:A)) -> TRUE | F24: =ISNUMBER(MATCH(D24,data!E:E)) -> TRUE | G24: Member States shall ensure that the total final energy consumption of all public bodies combined is reduced by at least 1.9% each year, when compared to 2021 | H24: 14 Member States reported data on public buildings in their national energy and climate progress reports (NECPRs). Missing data prevent drawing general conclusions or calculating aggregated data at the EU level. In terms of final energy, the short-term evolution indicates a general increase with some exceptions, such as the residential sector in Greece and Ireland. The first reporting deadline for the EED is at the end of 2024. | I24: On energy efficiency and amending Regulation (EU) 2023/955 (recast)
B25: Energy Efficiency | C25: #FFF2CC | D25: TA2.22 | E25: =ISNUMBER(MATCH(D25,data!A:A)) -> TRUE | F25: =ISNUMBER(MATCH(D25,data!E:E)) -> TRUE | G25: Member States shall collectively ensure a reduction of energy consumption of at least 11.7% in 2030 compared to the projections of the 2020 EU Reference Scenario | H25: Final energy consumption reached 940 Mtoe in 2022, a 2.8% decrease compared with 2021. According to the EC assessment of the NECPs, the current Member States drafts pledges would lead to 5.8% energy efficiency improvements in 2030, compared to the target of 11.7%. Therefore, acceleration is needed to reach the 2030 target. | I25: On energy efficiency and amending Regulation (EU) 2023/955 (recast)
B26: Energy Efficiency | C26: #FFF2CC | D26: TA2.23 | E26: =ISNUMBER(MATCH(D26,data!A:A)) -> TRUE | F26: =ISNUMBER(MATCH(D26,data!E:E)) -> TRUE | G26: Member States shall make efforts to collectively contribute to the indicative Union primary energy consumption target amounting to no more than 992.5 Mtoe in 2030 | H26: In 2022, primary energy consumption in the EU reached 1257 Mtoe, a 4.1% decrease compared with 2021, moving closer to the 2030 target. Following the decline registered in 2020 due to the impact of the pandemic across sectors, EU primary energy consumption increased again in 2021. The year 2022 shows better results than in 2019, before the pandemic, when primary energy consumption was at 1354 Mtoe and 36.5% away from the target. The 1257 Mtoe registered for primary energy consumption in 2022 was the second lowest level since 1990 (the first year for which data are available), and the lowest was in 2020 (1236 Mtoe). According to the EC assessment of the NECPs, the current drafts would lead to a gap of 75 Mtoe from the 2030 target. | I26: On energy efficiency and amending Regulation (EU) 2023/955 (recast)
... B44: Renewable Energy | C44: #FFF2CC | D44: TA2.9 | E44: =ISNUMBER(MATCH(D44,data!A:A)) -> TRUE | F44: =ISNUMBER(MATCH(D44,data!E:E)) -> TRUE | G44: Member States shall collectively ensure that the share of energy from renewable sources in the Union‚Äôs gross final consumption of energy in 2030 is at least 42.5% | H44: In 2022, renewable energy represented 23.0 % of energy consumed in the EU, up from 21.9% in 2021. This EU-level target has not been translated into binding national contributions. The target is to be achieved jointly by all Member States, building on their coordinated and combined action. According to the EC assessment of the draft NECPs, the current drafts would lead to a share of 38.6-39.3% of renewables in the energy mix by 2030. Reaching the 2030 target of 42.5% (and even more so the aspirational target of 45%) will require a much faster growth in the coming years. | I44: amending Directive (EU) 2018/2001, Regulation (EU) 2018/1999 and Directive 98/70/EC as regards the promotion of energy from renewable sources, and repealing Council Directive (EU) 2015/652
A45: TA3 - Industrial strategy for a clean and circular economy | B45: Waste Reduction - Municipal Waste | C45: #FFC4C5 | D45: TA3.1 | E45: =ISNUMBER(MATCH(D45,data!A:A)) -> TRUE | F45: =ISNUMBER(MATCH(D45,data!E:E)) -> TRUE | G45: Halve the amount of residual (non-recycled) municipal waste by 2030 | H45: For this target, 2020 was assumed as the reference year, since the new CEAP was published in March 2020. This target is also recalled in the 'Zero Pollution Action Plan'. The target aims at halving the amount of residual municipal waste by 2030. Assuming as a reference year the 2020, the residual municipal waste should be reduced from 119 to 59.5 Mtonnes. Looking at historical trends, the amount of residual municipal waste decreased by only 5% in the time frame 2012-2021 and slightly increased in the last seven years (2015-2021, +2.6%). Despite increasing recycling levels, the amount of waste generated is increasing at a higher pace [130]. | I45: A new Circular Economy Action Plan. For a cleaner and more competitive Europe
B46: Critical Raw Materials - Extraction & Import | C46: #FFC4C5 | D46: TA3.11 | E46: =ISNUMBER(MATCH(D46,data!A:A)) -> TRUE | F46: =ISNUMBER(MATCH(D46,data!E:E)) -> TRUE | G46: Diversify the Union‚Äôs imports of strategic raw materials with a view to ensuring that, by 2030, the Union‚Äôs annual consumption of each strategic raw material at any relevant stage of processing can rely on imports from several third countries | H46: Half of the 16 strategic raw materials have values above the 65% target, therefore there is a low diversification of sourcing countries. These include bismuth, gallium, lithium, magnesium, platinum group metals, and both heavy and light rare earth elements. | I46: Establishing a framework for ensuring a secure and sustainable supply of critical raw materials and amending Regulations (EU) 168/2013, (EU) 2018/858, 2018/1724 and (EU) 2019/1020
B47: Net-Zero Technology - Manufacturing | C47: #FFC4C5 | D47: TA3.12 | E47: =ISNUMBER(MATCH(D47,data!A:A)) -> TRUE | F47: =ISNUMBER(MATCH(D47,data!E:E)) -> TRUE | G47: By 2030, manufacturing capacity in the Union of the strategic net-zero technologies listed in the Annex approaches or reaches a benchmark of at least 40% of the Union‚Äôs annual deployment needs | H47: Target set in 2023, data is currently not available to assess this target. | I47: On establishing a framework of measures for strengthening Europe’s net-zero technology products manufacturing ecosystem (Net Zero Industry Act)
B48: Circularity/Recycling - Critical Raw Materials - Batteries Recycling | C48: #FFC4C5 | D48: TA3.13 | E48: =ISNUMBER(MATCH(D48,data!A:A)) -> TRUE | F48: =ISNUMBER(MATCH(D48,data!E:E)) -> TRUE | G48: By 2030, Union recycling capacity, including for all intermediate recycling steps, should be able of producing at least 25% of the Union's annual consumption of strategic raw materials | H48: The historical trends of the recycling capacity for strategic materials can be assessed by looking at the evolution of the End-of-Life Recycling Input Rate of strategic materials over time. Out of 16 strategic materials, the recycling capacity: - was above the 25% benchmark in 2022 for two materials (copper and tungsten), - was between 22% and 5% in 2022 for eight materials groups (cobalt, magnesium, manganese, nickel, titanium, platinum group metals, and both heavy and light rare earth elements) - was below 5% for six materials (bismuth, boron, gallium, germanium, lithium and natural graphite) | I48: A Green Deal Industrial Plan for the Net-Zero Age
B49: Circularity/Recycling - Critical Raw Materials - Batteries Recycling | C49: #FFC4C5 | D49: TA3.15 | E49: =ISNUMBER(MATCH(D49,data!A:A)) -> TRUE | F49: =ISNUMBER(MATCH(D49,data!E:E)) -> TRUE | G49: Producers of starting, lighting and ignition batteries, industrial batteries and electric vehicle batteries or, where appointed in accordance with Article 57(1), producer responsibility organisations, shall take back, free of charge and without an obligation on the end-user to buy a new battery | H49: Currently, there is no official monitoring system in place and therefore it is not possible to assess if the target will be reached. | I49: Concerning batteries and waste batteries, amending Directive 2008/98/EC and Regulation (EU) 2019/1020 and repealing Directive 2006/66/EC
B50: Circularity/Recycling - Critical Raw Materials - Batteries Recycling | C50: #FFC4C5 | D50: TA3.16 | E50: =ISNUMBER(MATCH(D50,data!A:A)) -> TRUE | F50: =ISNUMBER(MATCH(D50,data!E:E)) -> TRUE | G50: Producers of portable batteries or, where appointed in accordance with Article 57(1), producer responsibility organisations, shall attain, and maintain durably, at least the following collection targets for waste portable batteries | H50: The calculation methodology is under development and these targets will be updated accordingly, whilst maintaining the same level of ambition. Currently, there is no robust data to assess the distance to the targets (e.g. due to new types of batteries entering in the markets, longer lifetime of batteries, new applications). Assuming the ambition of the targets, attention might be paid in the implementa- tion phase at Member State level. | I50: Concerning batteries and waste batteries, amending Directive 2008/98/EC and Regulation (EU) 2019/1020 and repealing Directive 2006/66/EC
B51: Circularity/Recycling - Critical Raw Materials - Batteries Recycling | C51: #FFC4C5 | D51: TA3.17 | E51: =ISNUMBER(MATCH(D51,data!A:A)) -> TRUE | F51: =ISNUMBER(MATCH(D51,data!E:E)) -> TRUE | G51: Producers of LMT batteries or, where appointed in accordance with Article 57(1), producer responsibility organisations, shall attain, and maintain durably, at least the following collection targets of waste LMT batteries | H51: The calculation methodology is under development and these targets will be updated accordingly, whilst maintaining the same level of ambition. Considering that light means of transport batteries represent a new market and collection systems need to be adapted, currently it is not possible to assess whether these ambitious targets are reachable or not. | I51: Concerning batteries and waste batteries, amending Directive 2008/98/EC and Regulation (EU) 2019/1020 and repealing Directive 2006/66/EC
B52: Circularity/Recycling - Critical Raw Materials - Batteries Recycling | C52: #FFC4C5 | D52: TA3.18 | E52: =ISNUMBER(MATCH(D52,data!A:A)) -> TRUE | F52: =ISNUMBER(MATCH(D52,data!E:E)) -> TRUE | G52: For industrial batteries with a capacity greater than 2kWh, except those with exclusively external storage, electric vehicle batteries and starting, lighting and ignition batteries that contain cobalt, lead, lithium or nickel in active materials, the minimum recycled content percentage for each battery model per year and per manufacturing plant shall be | H52: The assessment methodology is under development. Therefore, it is not possible to assess whether all producers will be able to reach these targets. JRC internal calculations show that these targets are in principle feasible, although significant changes in the industrial production systems are needed. | I52: Concerning batteries and waste batteries, amending Directive 2008/98/EC and Regulation (EU) 2019/1020 and repealing Directive 2006/66/EC
B53: Circularity/Recycling - Critical Raw Materials - Batteries Recycling | C53: #FFC4C5 | D53: TA3.19 | E53: =ISNUMBER(MATCH(D53,data!A:A)) -> TRUE | F53: =ISNUMBER(MATCH(D53,data!E:E)) -> TRUE | G53: Any natural or legal person that places on the market products incorporating portable batteries shall ensure that those batteries are readily removable and replaceable by the end-user at any time during the lifetime of the product | H53: This target is ambitious with a very wide coverage of products, many of which are expected to be redesigned in order to be compliant. However, high uncertainty on distance to target lies with existence of derogations and the challenge to establish them at product-specific level. The Delegated Acts expected to specify deroga- tions are not yet in place. Verification and procedures to accept/reject derogation applications will also need to be defined in the Delegated Acts. | I53: Concerning batteries and waste batteries, amending Directive 2008/98/EC and Regulation (EU) 2019/1020 and repealing Directive 2006/66/EC
B54: Circularity/Recycling - Critical Raw Materials - Batteries Recycling | C54: #FFC4C5 | D54: TA3.20 | E54: =ISNUMBER(MATCH(D54,data!A:A)) -> TRUE | F54: =ISNUMBER(MATCH(D54,data!E:E)) -> TRUE | G54: Recycling shall achieve at least the following targets for recycling efficiency: No later than 31 December 2025 - 75% by average weight of lead-acid batteries - 80% by average weight of nickel-cadmium batteries - 50% by average weight of other waste batteries No later than 31 December 2030 - 80% by average weight of lead-acid batteries Regulation (EU) 2023/1542 | H54: Based on current draft guidance for calculation and verification rules for recycling efficiency, the targets for lead-acid, nickel-cadmium and other waste batteries are feasible. Since, for lead-acid batteries, the battery chemistry and related recycling technologies are fully mature and efficient. For both nickel-cadmium and other waste batteries, it will be important to monitor the performances due to the evolving market for these chemistries. | I54: Concerning batteries and waste batteries, amending Directive 2008/98/EC and Regulation (EU) 2019/1020 and repealing Directive 2006/66/EC
B55: Circularity/Recycling - Critical Raw Materials - Batteries Recycling | C55: #FFC4C5 | D55: TA3.21 | E55: =ISNUMBER(MATCH(D55,data!A:A)) -> TRUE | F55: =ISNUMBER(MATCH(D55,data!E:E)) -> TRUE | G55: Recycling shall achieve at least the following targets for recycling efficiency: - No later than 31 December 2025, 65% by average weight of lithium-based batteries - No later than 31 December 2030, 70% by average weight of lithium-based batteries. Regulation (EU) 2023/1542 | H55: The 2025 target for lithium-based batteries is in principle feasible, however due to the increasing diversity of lithium-based batteries on the market, it is important to closely monitor the performance towards the target. Furthermore, there are some improvement opportunities when data is available, recycling systems are established and when the target is revised by 2027. | I55: Concerning batteries and waste batteries, amending Directive 2008/98/EC and Regulation (EU) 2019/1020 and repealing Directive 2006/66/EC
B56: Circularity/Recycling - Critical Raw Materials - Batteries Recycling | C56: #FFC4C5 | D56: TA3.22 | E56: =ISNUMBER(MATCH(D56,data!A:A)) -> TRUE | F56: =ISNUMBER(MATCH(D56,data!E:E)) -> TRUE | G56: All recycling shall achieve at least the following targets for recovery of materials: - No later than 31 December 2027, 90% for cobalt, copper, lead, nickel - No later than 31 December 2031, 95% for cobalt, copper, lead, nickel Regulation (EU) 2023/1542 | H56: Based on the current draft guidance for the calculation and verification rules for material recovery, the targets for cobalt, copper, lead and nickel are feasible. | I56: Concerning batteries and waste batteries, amending Directive 2008/98/EC and Regulation (EU) 2019/1020 and repealing Directive 2006/66/EC
B57: Circularity/Recycling - Critical Raw Materials - Batteries Recycling | C57: #FFC4C5 | D57: TA3.23 | E57: =ISNUMBER(MATCH(D57,data!A:A)) -> TRUE | F57: =ISNUMBER(MATCH(D57,data!E:E)) -> TRUE | G57: All recycling shall achieve at least the following targets for recovery of materials, 50% for lithium, no later than 31 December 2027 and 80% for lithium no later than 31 December 2031. Regulation (EU) 2023/1542 | H57: Based on the current draft guidance for the calculation and verification rules, the target for lithium is in principle feasible. Significant investments in lithium recycling systems are required. | I57: Concerning batteries and waste batteries, amending Directive 2008/98/EC and Regulation (EU) 2019/1020 and repealing Directive 2006/66/EC
... B81: Critical Raw Materials - Extraction & Import | C81: #FFC4C5 | D81: TA3.9 | E81: =ISNUMBER(MATCH(D81,data!A:A)) -> TRUE | F81: =ISNUMBER(MATCH(D81,data!E:E)) -> TRUE | G81: By 2030, Union processing capacity, including for all intermediate processing steps, should be able of producing at least 40% of the Union‚Äôs annual consumption of strategic raw materials | H81: The historical time trends (2011-2022) for the EU self-sufficiency at processing phase for the 16 strategic materials can be extracted based on data from [121] and [122] and [123]. Results show that: - The EU’s self-sufficiency for copper, cobalt and germanium was above the benchmark in 2022. For copper, this value has been stably above 80% in the period 2011-2022. For cobalt and germanium, the trend was fluctuating and more unstable, but increasing in between 2018 and 2022. - The EU’s self-sufficiency was below the benchmark in 2022 for bismuth, boron, gallium and platinum group metals, with gallium showing a drastic decrease from 2011 (100%) to 2022 (2%). - The EU has no self-sufficiency to process lithium, magnesium, natural graphite, titanium, and both heavy and light rare earth elements, while there is no sufficient data available for tungsten, nickel and manganese. | I81: Establishing a framework for ensuring a secure and sustainable supply of critical raw materials and amending Regulations (EU) 168/2013, (EU) 2018/858, 2018/1724 and (EU) 2019/1020
A82: TA4 - Sustainable and smart mobility | B82: Biofuels | C82: #E4CCEC | D82: TA4.1 | E82: =ISNUMBER(MATCH(D82,data!A:A)) -> TRUE | F82: =ISNUMBER(MATCH(D82,data!E:E)) -> TRUE | G82: Achieve an annual production of sustainable biomethane of 35 billion cubic meters by 2030 | H82: In 2021, the total biomethane production in the EU was 3.5 billion cubic meters, produced in about 1300 biomethane plants. Production increased in 2022 to reach 4.2 bcm. In order to reach 35 billion cubic meters, an estimate of 5000 additional plants are required. . | I82: amending Directive (EU) 2018/2001, Regulation (EU) 2018/1999 and Directive 98/70/EC as regards the promotion of energy from renewable sources, and repealing Council Directive (EU) 2015/652
B83: Energy Efficiency | C83: #E4CCEC | D83: TA4.10 | E83: =ISNUMBER(MATCH(D83,data!A:A)) -> TRUE | F83: =ISNUMBER(MATCH(D83,data!E:E)) -> TRUE | G83: EU fisheries are encouraged to continue the positive trend, as observed for the period 2009-2019, towards reducing fuel intensity by reducing the fossil-fuel consumption per kg of landed product for at least an additional 15% for the period 2019-2030. Energy Transition of the EU Fisheries and Aquaculture sector | H83: The Communication notes that "Fisheries and aquaculture operators began reducing their energy intensity between 2009 and 2014, but the progress they made has stagnated in recent years. Therefore, there is a need to accelerate the energy transition". In turn, this statement grounds on the JRC science for policy report "The 2022 Annual Economic Report on the EU Fishing Fleet” [161] by the Scientific, Technical and Economic Committee for Fisheries, assessing that the sector fuel intensity (i.e. fuel consumption per tonne landed) dropped by more than 15% between 2009 and 2014, but that this trend has stagnated since then. | I83: On the Energy Transition of the EU Fisheries and Aquaculture sector
B84: Transport Logistics | C84: #E4CCEC | D84: TA4.11 | E84: =ISNUMBER(MATCH(D84,data!A:A)) -> TRUE | F84: =ISNUMBER(MATCH(D84,data!E:E)) -> TRUE | G84: Reduce the average door-to-door cost of combined transport operations by at least 10% within 7 years Proposal for a Directive to support framework for intermodal transport of goods | H84: EU shipping emissions increased by 5.6% in 2021 from the previous year, rebounding from the COVID-19 induced slump of 2020. The target for 2025 seems unlikely to be reached. The EEA projections suggest that, even with measures currently planned in the Member States, emissions from domestic navigation are projected to remain relatively stable in the coming years. International maritime transport emissions are projected to continue increasing. | I84: Amending Council Directive 92/106/EEC as regards a support framework for intermodal transport of goods and Regulation (EU) 2020/1056 of the European Parliament and the Council as regards calculation of external costs savings and generation of aggregated data
B85: Net-Zero Technology - Road Vehicles | C85: #E4CCEC | D85: TA4.13 | E85: =ISNUMBER(MATCH(D85,data!A:A)) -> TRUE | F85: =ISNUMBER(MATCH(D85,data!E:E)) -> TRUE | G85: For [...] ‚Äúurban buses‚Äù manufacturers shall comply with the 90% (in the reporting period 2030-2034) and 100% (as from 2035) minimum shares in their fleet of new heavy-duty vehicles Regulation (EU) 2024/1610 | H85: Several plants are being built to produce sustainable aviation fuels and sustainable aviation fuels are tested by companies. The contribution of aviation fuels is practically negligible currently. No sustainable biofuel use was reported in Eurostat in aviation in 2021. | I85: Amending Regulation (EU) 2019/1242 as regards strengthening the CO₂ emission performance standards for new heavy-duty vehicles and integrating reporting obligations, and repealing Regulation (EU) 2018/956
B86: GHG Reduction - Transports | C86: #E4CCEC | D86: TA4.15 | E86: =ISNUMBER(MATCH(D86,data!A:A)) -> TRUE | F86: =ISNUMBER(MATCH(D86,data!E:E)) -> TRUE | G86: The average CO2 emissions of the Union fleet of new heavy-duty motor vehicles [...], off-road vehicles and off-road special purpose vehicles shall be reduced by the following percentages compared to the average CO2 emissions of the reporting period of the year 2019: (a) 15% for vehicle sub-groups 4-UD, 4-RD, 4-LH, 5-RD, 5-LH, 9-RD, 9-LH, 10-RD and 10-LH for the reporting periods of the years 2025 to 2029, (b) 45% for all vehicle sub-groups other than vocational vehicles for the reporting periods of the years 2030 to 2034, (c) 65% for all vehicle sub-groups for the reporting periods of the years 2035 to 2039, (d) 90% for all vehicle sub-groups for the reporting periods of the year 2040 onwards Regulation (EU) 2024/1610 | H86: The average specific CO2 emissions of new heavy-duty vehicles in groups 4, 5, 9 and 10 has decreased by 0.55%, from 52.75g/t.km in 2019 to 52.45g/t.km in 2020. The rate of decrease is therefore slow and acceleration is needed to achieve the targets. | I86: Amending Regulation (EU) 2019/1242 as regards strengthening the CO₂ emission performance standards for new heavy-duty vehicles and integrating reporting obligations, and repealing Regulation (EU) 2018/956
B87: Biofuels | C87: #E4CCEC | D87: TA4.18 | E87: =ISNUMBER(MATCH(D87,data!A:A)) -> TRUE | F87: =ISNUMBER(MATCH(D87,data!E:E)) -> TRUE | G87: The share of biofuels and biogas produced from the feedstock listed in Part B of Annex IX in the energy content of fuels and electricity supplied to the transport sector shall, except in Cyprus and Malta, be limited to 1.7%. Directive (EU) 2023/2413 | H87: The EU share (including Cyprus and Malta) was 1.28% in 2021, it increased to 1.35% in 2022. This target is currently on track. | I87: Biofuels - Directive (EU) 2023/2413
B88: Energy Efficiency | C88: #E4CCEC | D88: TA4.19 | E88: =ISNUMBER(MATCH(D88,data!A:A)) -> TRUE | F88: =ISNUMBER(MATCH(D88,data!E:E)) -> TRUE | G88: The yearly quantity of aviation fuel uplifted by a given aircraft operator at a given Union airport shall be at least 90% of the yearly aviation fuel required, to avoid tankering practices which would bring additional emissions from extra weight. Regulation (EU) 2023/2405 | H88: No data available | I88: Aviation Fuel - Regulation (EU) 2023/2405
B89: Renewable Energy - Hydrogen Production | C89: #E4CCEC | D89: TA4.20 | E89: =ISNUMBER(MATCH(D89,data!A:A)) -> TRUE | F89: =ISNUMBER(MATCH(D89,data!E:E)) -> TRUE | G89: In the first phase, from 2020 up to 2024, the strategic objective is to install at least 6 GW of renewable hydrogen electrolysers in the EU. In the second phase, from 2025 up to 2030, the strategic objective is to install at least 40 GW of renewable hydrogen electrolysers. A Hydrogen Strategy for a climate-neutral Europe | H89: Initiatives are ongoing and deployment of electrolysers is increasing, but it is unlikely that the target of deploying 6 GW of hydrogen generation capacity will be reached by the end of 2024. | I89: A hydrogen strategy for a climate-neutral Europe
B90: Energy Infrastructure | C90: #E4CCEC | D90: TA4.25 | E90: =ISNUMBER(MATCH(D90,data!A:A)) -> TRUE | F90: =ISNUMBER(MATCH(D90,data!E:E)) -> TRUE | G90: Member States shall ensure that, at the end of each year, the following power output targets are met cumulatively: (a) for each light-duty battery electric vehicle registered in their territory, a total power output of at least 1.3 kW is provided through publicly accessible recharging stations, and (b) for each light-duty plug-in hybrid vehicle registered in their territory, a total power output of at least 0.80 kW is provided through publicly accessible recharging stations. Regulation (EU) 2023/1804 | H90: Based on charging infrastructure data from Eco-Movement 2022 and estimates of electric vehicles on the roads, most Member States are already compliant with this fleet-based target (see European Alter-native Fuels Observatory – Target tracker). Research also highlights that the total power output needed per electric vehicle (including battery electric vehicles and plug-in hybrid vehicles) is highly dependent on the share of electric cars and vans on the road, with AFIR targets on cumulative power outputs per vehicle being sufficient in the long term (when a rise in the market share of battery electric vehicles and plug-in hybrid vehicles is expected) [157]. | I90: On the deployment of alternative fuels infrastructure, and repealing Directive 2014/94/EU of the European Parliament and of the Council
B91: Energy Infrastructure | C91: #E4CCEC | D91: TA4.26 | E91: =ISNUMBER(MATCH(D91,data!A:A)) -> TRUE | F91: =ISNUMBER(MATCH(D91,data!E:E)) -> TRUE | G91: Member States shall ensure that along the TEN-T core and comprehensive network, publicly accessible recharging pools dedicated to light-duty vehicles deployed in each direction of travel with a maximum distance of 60 km in-between them offering a power output of at least 600kW and including at least one recharging point with an individual power output of at least 150 kW. Regulation (EU) 2023/1804 | H91: The average specific CO2 emissions of new heavy-duty vehicles in groups 4, 5, 9 and 10 has decreased by 0.55%, from 52.75g/t.km in 2019 to 52.45g/t.km in 2020. The rate of decrease is therefore slow and acceleration is needed to achieve the targets. | I91: On the deployment of alternative fuels infrastructure, and repealing Directive 2014/94/EU of the European Parliament and of the Council
B92: Energy Infrastructure | C92: #E4CCEC | D92: TA4.27 | E92: =ISNUMBER(MATCH(D92,data!A:A)) -> TRUE | F92: =ISNUMBER(MATCH(D92,data!E:E)) -> TRUE | G92: Member States shall ensure that, by 31 December 2030 (with intermediate 2025 and 2027 targets), along the TEN-T core road network, publicly accessible recharging pools dedicated to heavy-duty electric vehicles are deployed in each direction of travel with a maximum distance of 60 km between them [...]. Along the TEN-T comprehensive road network, recharging pools dedicated to heavy-duty electric vehicles are deployed in each direction of travel with a maximum distance of 100 km between them and each recharging pool offers a power output of at least 1.500 kW and includes at least one recharging point with an individual power output of at least 350 kW. Regulation (EU) 2023/1804 | H92: The EU share (including Cyprus and Malta) was 1.28% in 2021, it increased to 1.35% in 2022. This target is currently on track. | I92: On the deployment of alternative fuels infrastructure, and repealing Directive 2014/94/EU of the European Parliament and of the Council
B93: Energy Infrastructure | C93: #E4CCEC | D93: TA4.28 | E93: =ISNUMBER(MATCH(D93,data!A:A)) -> TRUE | F93: =ISNUMBER(MATCH(D93,data!E:E)) -> TRUE | G93: By 31 December 2030, in each safe and secure parking area at least four publicly accessible recharging stations dedicated to heavy-duty electric vehicles with an individual power output of at least 100 kW are deployed. Regulation (EU) 2023/1804 | H93: No data available | I93: On the deployment of alternative fuels infrastructure, and repealing Directive 2014/94/EU of the European Parliament and of the Council
B94: Energy Infrastructure | C94: #E4CCEC | D94: TA4.29 | E94: =ISNUMBER(MATCH(D94,data!A:A)) -> TRUE | F94: =ISNUMBER(MATCH(D94,data!E:E)) -> TRUE | G94: By 31 December 2030, in each urban node publicly accessible recharging points dedicated to heavy-duty electric vehicles with an aggregated power output of at least 1 800 kW are deployed, provided by recharging stations with an individual power output of at least 150 kW. Regulation (EU) 2023/180 | H94: Initiatives are ongoing and deployment of electrolysers is increasing, but it is unlikely that the target of deploying 6 GW of hydrogen generation capacity will be reached by the end of 2024. | I94: On the deployment of alternative fuels infrastructure, and repealing Directive 2014/94/EU of the European Parliament and of the Council
... B106: GHG Reduction - Transports | C106: #E4CCEC | D106: TA4.9 | E106: =ISNUMBER(MATCH(D106,data!A:A)) -> TRUE | F106: =ISNUMBER(MATCH(D106,data!E:E)) -> TRUE | G106: Cut the emissions of transport sector by 90% by 2050 relative to 1990. Sustainable and Smart Mobility Strategy | H106: Following six years of steady growth in greenhouse gas emissions from the EU’s transport sector, transport emissions dropped substantially in 2020 because of reduced activity during the COVID-19 pandemic. In 2022 they were still 6% below 2019 levels. However, Eurostat quarterly GHG emission data shows that this rebound continued in 2023. According to the Report “Towards EU climate neutrality: progress, policy gaps and opportunities” by the European Scientific Advisory Board on Climate Change, the average rate of emission reduction since 2005 (-2 MtCO2e per year) should be more than 10 times higher (-26 MtCO2e per year in 2023-2030) to be consistent with the trajectories towards the overall 2030 net GHG emission reduction target by the EU Climate Law. When considering the 90% reduction objective for transport GHG emissions by 2050, the average rate of emission reduction should be higher (-31 MtCO2e in 2031-2050). | I106: Sustainable and Smart Mobility Strategy – putting European transport on track for the future
A107: TA5 - Greening the Common Agricultural Policy - Farm to Fork Strategy | B107: Renewable Energy | C107: #C6F0CE | D107: TA5.10 | E107: =ISNUMBER(MATCH(D107,data!A:A)) -> TRUE | F107: =ISNUMBER(MATCH(D107,data!E:E)) -> TRUE | G107: Energy: Increase renewable energy in the agriculture and food sector. Adopt energy efficiency solutions in the agriculture and food sector, by reducing energy consumption. | H107: Initiatives are ongoing and deployment of electrolysers is increasing, but it is unlikely that the target of deploying 6 GW of hydrogen generation capacity will be reached by the end of 2024. | I107: A Farm to Fork Strategy
B108: Biodiversity Protection & Conservation | C108: #C6F0CE | D108: TA5.11 | E108: =ISNUMBER(MATCH(D108,data!A:A)) -> TRUE | F108: =ISNUMBER(MATCH(D108,data!E:E)) -> TRUE | G108: Biodiversity conservation and restoration of natural resources: Protect the environment and restore natural resources. Preserve biodiversity and reduce biodiversity loss. | H108: Based on charging infrastructure data from Eco-Movement 2022 and estimates of electric vehicles on the roads, most Member States are already compliant with this fleet-based target (see European Alter-native Fuels Observatory – Target tracker). Research also highlights that the total power output needed per electric vehicle (including battery electric vehicles and plug-in hybrid vehicles) is highly dependent on the share of electric cars and vans on the road, with AFIR targets on cumulative power outputs per vehicle being sufficient in the long term (when a rise in the market share of battery electric vehicles and plug-in hybrid vehicles is expected) [157]. | I108: A Farm to Fork Strategy
B109: Food quality | C109: #C6F0CE | D109: TA5.12 | E109: =ISNUMBER(MATCH(D109,data!A:A)) -> TRUE | F109: =ISNUMBER(MATCH(D109,data!E:E)) -> TRUE | G109: Genetic biodiversity of food production systems: Secure and ensure access to a range of quality seeds for plant varieties in order to adapt to the pressures of climate change. | H109: The average specific CO2 emissions of new heavy-duty vehicles in groups 4, 5, 9 and 10 has decreased by 0.55%, from 52.75g/t.km in 2019 to 52.45g/t.km in 2020. The rate of decrease is therefore slow and acceleration is needed to achieve the targets. | I109: A Farm to Fork Strategy
B110: Waste Reduction - Food Waste | C110: #C6F0CE | D110: TA5.13 | E110: =ISNUMBER(MATCH(D110,data!A:A)) -> TRUE | F110: =ISNUMBER(MATCH(D110,data!E:E)) -> TRUE | G110: Reduce food waste. Prevent food loss and waste. Halve per capita food waste at retail and consumer levels* *See also Directive (EU) 2018/851 on waste with a target on food waste reduction of 30% by 2025 | H110: The EU share (including Cyprus and Malta) was 1.28% in 2021, it increased to 1.35% in 2022. This target is currently on track. | I110: A Farm to Fork Strategy
B111: Circularity/Recycling | C111: #C6F0CE | D111: TA5.14 | E111: =ISNUMBER(MATCH(D111,data!A:A)) -> TRUE | F111: =ISNUMBER(MATCH(D111,data!E:E)) -> TRUE | G111: Circular economy: Scale-up and promote sustainable and socially responsible production methods and circular business models in food processing and retail. | H111: No data available | I111: A Farm to Fork Strategy
B112: Food quality | C112: #C6F0CE | D112: TA5.15 | E112: =ISNUMBER(MATCH(D112,data!A:A)) -> TRUE | F112: =ISNUMBER(MATCH(D112,data!E:E)) -> TRUE | G112: Consumption footprint: Reduce the environmental and climate footprint of the EU food system, operating within planetary boundaries. Reduce the EU‚Äôs contribution to global deforestation and forest degradation. | H112: According to JRC study [183], the EU food system is transgressing several planetary boundaries including climate change and those related to novel entities (particulate matter, freshwater ecotoxicity). The Consumption Footprint related to food consumption has shown an increasing trend since 2010, with the consumption of animal-based products dominating the impacts (around 70%). This increasing trend was common for most of the Member States (20 out of 27) [184]. Indicator: Consumption Footprint (Food) (Source: JRC). | I112: A Farm to Fork Strategy
B113: Social Security - Workers Protection | C113: #C6F0CE | D113: TA5.16 | E113: =ISNUMBER(MATCH(D113,data!A:A)) -> TRUE | F113: =ISNUMBER(MATCH(D113,data!E:E)) -> TRUE | G113: Income distribution: Ensure fair income and salaries. Improve income of primary producers to ensure their sustainable livelihood. | H113: This indicator compares agricultural income to average wages in the economy and provides an estimate of the average income opportunities that a person would have outside of agriculture. It has increased from 31% to 52% between 2005 and 2021 at the EU level, reflecting a CAGR of 3% in this time frame. However, there are discrepancies among Member States. While in certain Member States, such as Hungary and France, farmers' income compared to other wages in the economy has grown more than the EU average, in other Member States like Italy and Belgium, have remained below the EU average or have shown a decreasing trend (e.g. Estonia and Austria). In addition, although the average farm income per worker in the EU has steadily increased over the past decade (by 56% from 2013 to 2021), income levels do not only vary significantly across EU countries, but also across the farming sector and farm size. In particular, farm economic size significantly influences income as higher costs per hectare associated with larger farms are compensated by higher production, leading to greater overall profitability. Indicator: Farmers income compared to wages in the rest of the economy (Source: DG AGRI). | I113: A Farm to Fork Strategy
B114: Competitive Agriculture | C114: #C6F0CE | D114: TA5.17 | E114: =ISNUMBER(MATCH(D114,data!A:A)) -> TRUE | F114: =ISNUMBER(MATCH(D114,data!E:E)) -> TRUE | G114: Sectorial growth: Help farmers and fishers to strengthen their position in the supply chain and to capture a fair share of the added value of sustainable production | H114: This indicator measures the economic contribution in the agriculture, fishing and aquaculture, as well as the food, beverage, and tobacco sectors. The food, beverage, and tobacco sectors constitute the largest portion of the overall agri-food value chain (over 50%), followed by the agriculture sector. The total value added in the food and agriculture sectors has Increased from 340K in 2008 to 433.5K in 2020 in the EU, with a CAGR of 2%. The compound growth in the manufactured food sector has been higher (2.5%) than the growth in the agriculture sector (1.5%). Indicator: Value added along the food chain (Source: JRC). | I114: A Farm to Fork Strategy
B115: Competitive Agriculture | C115: #C6F0CE | D115: TA5.18 | E115: =ISNUMBER(MATCH(D115,data!A:A)) -> TRUE | F115: =ISNUMBER(MATCH(D115,data!E:E)) -> TRUE | G115: Market power and business structure: Improve agricultural rules that strengthen the position of farmers (e.g. producers of products with geographical indications), their cooperatives and producer organisations in the food supply chain. | H115: This indicator is important to assess the level of investment and development in the agricultural sector. Among Member States, the level of gross fixed capital formation varies. Most Member States surpass the EU average. While countries such as France and Germany have the highest capital formation in agriculture, some Member States lag behind e.g. Czechia, Bulgaria and Estonia. In the EU, gross fixed capital formation in agriculture has increased from EUR 44 Billion in 2005 to EUR 68 Billion in 2022, corresponding to a CAGR of 2.8% and a 55% percentage increase. The growth rates also vary across Member States. As expected, the countries with highest capital formation show limited growth trend e.g. Germany, while the highest growth rates are observed in countries that had lower starting values e.g. Romania, Bulgaria. Indicator: Gross fixed capital formation in agriculture (Source: DG AGRI). | I115: A Farm to Fork Strategy
B116: Food affordability | C116: #C6F0CE | D116: TA5.19 | E116: =ISNUMBER(MATCH(D116,data!A:A)) -> TRUE | F116: =ISNUMBER(MATCH(D116,data!E:E)) -> TRUE | G116: Price: Preserve the price affordability of food. | H116: The annual average of food prices, indexed to 2015, has increased from 80% (2005) to 125% (2022), an average yearly inflation of almost 2.5%. Since 2015, food prices have risen by 25%, and the biggest increase has taken place in 2022. Indicator: Consumer food inflation (Source: Eurostat). | I116: A Farm to Fork Strategy
B117: Food quality - Animal Welfare | C117: #C6F0CE | D117: TA5.2 | E117: =ISNUMBER(MATCH(D117,data!A:A)) -> TRUE | F117: =ISNUMBER(MATCH(D117,data!E:E)) -> TRUE | G117: Reduce overall EU sales of antimicrobials for farmed animals and in aquaculture by 50% by 2030. | H117: Indicator: Sales of antimicrobials for food producing animals (Source: EMA). According to the 13th European Surveillance of Veterinary Antimicrobial Consumption report, the overall sales of antimicrobials for use in food-producing animals within the EU have fallen between 2018 and 2022 by 28.3%. During this period, the overall EU sales have thus reached more than half of the reduction target, which shows that the target can be achieved by 2030. | I117: A Farm to Fork Strategy
B118: Competitive Agriculture | C118: #C6F0CE | D118: TA5.20 | E118: =ISNUMBER(MATCH(D118,data!A:A)) -> TRUE | F118: =ISNUMBER(MATCH(D118,data!E:E)) -> TRUE | G118: Trade: Foster the competitiveness of the EU supply sector. | H118: The EU agri-food trade balance has shown stable growth over the last twenty years, despite a marginal decrease in 2022. It has reached a record level in 2023, with a total surplus of EUR 70.1 billion. While the overall agri-food trade balance shows a surplus, there are variations at the category level. The EU has a trade deficit in several product categories, with the most significant deficits observed in oilseeds and protein crops, and some fruits and nuts. The surplus is spread across product categories, driven mainly by cereal preparations, dairy products, and wine. Indicator: Agricultural and food products trade balance (Source: Eurostat). | I118: A Farm to Fork Strategy
B119: Digitalisation | C119: #C6F0CE | D119: TA5.21 | E119: =ISNUMBER(MATCH(D119,data!A:A)) -> TRUE | F119: =ISNUMBER(MATCH(D119,data!E:E)) -> TRUE | G119: Digitalisation and knowledge transfer. Ensure access to fast broadband to all farmers and all rural areas to achieve the objective of 100% access by 2025 (enabler for jobs, businesses, investments, improvement in quality of life in rural areas and enabler to mainstream precision farming and use of artificial intelligence | H119: Indicator: Rural next generation access (NGA) broadband coverage, as a % of households (Source: DG DIGIT). Next generation access broadband availability has significantly improved over the past decade, with the percentage of households having access increasing from 18% of rural households in 2013 to 73% in 2022. However, the objective of achieving 100% coverage by 2025 is at risk at the current pace. Most Member States remain above the EU average of 73%. However, despite showing growth in the last decade, some Member States such as France (2013: 16%, 2022: 59%), Poland (2013: 18%, 2022: 40%), and Croatia (2013: >1%, 2022: 52%), still lag behind. | I119: A Farm to Fork Strategy
... B138: Food quality | C138: #C6F0CE | D138: TA5.9 | E138: =ISNUMBER(MATCH(D138,data!A:A)) -> TRUE | F138: =ISNUMBER(MATCH(D138,data!E:E)) -> TRUE | G138: Increase organic farming with the aim to achieve at least 25% of total farmland under organic farming by 2030 Target in Common with Biodiversity Strategy (see Thematic Area 6) | H138: No data available | I138: A Farm to Fork Strategy
A139: TA6 - Preserving and protecting biodiversity | B139: Biodiversity Protection & Conservation | C139: #DBCFC1 | D139: TA6.1 | E139: =ISNUMBER(MATCH(D139,data!A:A)) -> TRUE | F139: =ISNUMBER(MATCH(D139,data!E:E)) -> TRUE | G139: 1.a Legally protect a minimum of 30% of the EU‚Äôs land area | H139: The 26% of EU’s land area is covered by protected areas, including 18.6% by Natura 2000 designated protected areas and 17.3% by nationally designated protected areas. If the designation of protected areas continues at the rate seen in the past decade (1.7 percentage points increase since 2011), the target will not be met [209]. | I139: EU Biodiversity Strategy for 2030
B140: Terrestrial Ecosystems Restoration - Agricultural Ecosystems | C140: #DBCFC1 | D140: TA6.10 | E140: =ISNUMBER(MATCH(D140,data!A:A)) -> TRUE | F140: =ISNUMBER(MATCH(D140,data!E:E)) -> TRUE | G140: 7. At least 10% of agricultural area is under high-diversity landscape features | H140: The JRC has developed an indicator [212] to monitor progress in the share of agricultural area covered by landscape features, showing that currently, at the EU level, 5.6% of agricultural land is covered by landscape features. However, this indicator does not capture high-diversity landscape features and no temporal trend is available, so at this stage no conclusion can be made regarding the likelihood to reach the target. | I140: EU Biodiversity Strategy for 2030
B141: Terrestrial Ecosystems Restoration - Forests | C141: #DBCFC1 | D141: TA6.11 | E141: =ISNUMBER(MATCH(D141,data!A:A)) -> TRUE | F141: =ISNUMBER(MATCH(D141,data!E:E)) -> TRUE | G141: 9. Three billion trees are planted in the EU, in full respect of ecological principles | H141: See table above. | I141: EU Biodiversity Strategy for 2030
B142: Terrestrial Ecosystems Restoration - Rivers | C142: #DBCFC1 | D142: TA6.13 | E142: =ISNUMBER(MATCH(D142,data!A:A)) -> TRUE | F142: =ISNUMBER(MATCH(D142,data!E:E)) -> TRUE | G142: 11. At least 25.000 km of free-flowing rivers are restored | H142: See table above. | I142: EU Biodiversity Strategy for 2030
B143: Biodiversity Protection & Conservation | C143: #DBCFC1 | D143: TA6.14 | E143: =ISNUMBER(MATCH(D143,data!A:A)) -> TRUE | F143: =ISNUMBER(MATCH(D143,data!E:E)) -> TRUE | G143: 12. There is a 50% reduction in the number of Red List species threatened by Invasive Alien Species (IAS) | H143: The expected acceleration in the number of alien species introductions and establishment due to global trade (including web trade), travel, and climate change, can lead to increased adverse impacts on biodiversity and ecosystems, human health and the economy. The Regulation (EU) 1143/2014 (IAS Regulation) includes a set of measures to be taken across the EU in relation to IAS, aiming to prevent, minimise and mitigate their adverse impacts. The implementation is underpinned by EASIN (European Alien Species Information Network), which also hosts the European early warning system on IAS of Union concern. The actions fostered by the EU biodiversity Strategy for 2023 aim at stepping up the IAS Regulation and other relevant legislation and international agreements with the objective of managing established IAS, decreasing the number of Red List species they threaten. | I143: EU Biodiversity Strategy for 2030
B144: Improve Soils Health | C144: #DBCFC1 | D144: TA6.15 | E144: =ISNUMBER(MATCH(D144,data!A:A)) -> TRUE | F144: =ISNUMBER(MATCH(D144,data!E:E)) -> TRUE | G144: 13. The losses of nutrients from fertilisers are reduced by 50%, resulting in the reduction of the use of fertilisers by at least 20% | H144: The average river nitrate concentration in Europe decreased steadily over the period 1992-2009 but has levelled off since then. Agriculture remains the main contributor to nitrogen pollution, but the EU Nitrates Directive and national measures have contributed to lower concentrations. However, the apparent stabilisation in recent years calls for further measures | I144: EU Biodiversity Strategy for 2030
B145: Biodiversity Protection & Conservation - Urban Nature | C145: #DBCFC1 | D145: TA6.16 | E145: =ISNUMBER(MATCH(D145,data!A:A)) -> TRUE | F145: =ISNUMBER(MATCH(D145,data!E:E)) -> TRUE | G145: 14. Cities with at least 20.000 inhabitants have an ambitious Urban Greening Plan | H145: No data is yet available. | I145: EU Biodiversity Strategy for 2030
B146: Biodiversity Protection & Conservation - Fisheries | C146: #DBCFC1 | D146: TA6.2 | E146: =ISNUMBER(MATCH(D146,data!A:A)) -> TRUE | F146: =ISNUMBER(MATCH(D146,data!E:E)) -> TRUE | G146: 1.b Legally protect a minimum of 30% of the EU's sea area | H146: 12% of EU's sea area is currently covered by protected areas, including 9% by Natura 2000 designated protected areas and 4.5% by nationally designated protected areas. | I146: EU Biodiversity Strategy for 2030
B147: Biodiversity Protection & Conservation - Fisheries | C147: #DBCFC1 | D147: TA6.28 | E147: =ISNUMBER(MATCH(D147,data!A:A)) -> TRUE | F147: =ISNUMBER(MATCH(D147,data!E:E)) -> TRUE | G147: In accordance with the CFP, it is crucial to continue and accelerate the work of rebuilding and keeping fish stocks above MSY levels | H147: In the Northeast Atlantic (both EU and non-EU waters), stock status has significantly improved from 2003 to 2021, but still an important share of stocks is overexploited. | I147: The common fisheries policy today and tomorrow: a Fisheries and Oceans Pact towards sustainable, science-based, innovative and inclusive fisheries management
B148: Terrestrial Ecosystems Restoration | C148: #DBCFC1 | D148: TA6.29 | E148: =ISNUMBER(MATCH(D148,data!A:A)) -> TRUE | F148: =ISNUMBER(MATCH(D148,data!E:E)) -> TRUE | G148: Terrestrial ecosystems. Member States shall put in place [...] measures [...] to jointly cover, as a Union target, throughout the areas and ecosystems [...] defined in Art. 2, by 2030, at least 20% of land areas in need of restoration and, by 2050, all ecosystems in need of restoration. | H148: Data on restoration has not been systematically collected at the EU level yet. | I148: Ensuring resilient and sustainable use of EU's natural resources
B149: Biodiversity Protection & Conservation | C149: #DBCFC1 | D149: TA6.3 | E149: =ISNUMBER(MATCH(D149,data!A:A)) -> TRUE | F149: =ISNUMBER(MATCH(D149,data!E:E)) -> TRUE | G149: 2.a Strictly protect at least a third of the EU'S protected areas | H149: Indicators are missing to check whether the EU is on track or not. Seven out of the nine actions set in the EU BDS to foster biodiversity protection in the EU still need to be implemented by 2030, but they all appear on track so far. Member States did not report official information reported to EEA. An independent scientific assessment [210] shows that currently only 3.5 % of protected areas are strictly protected. | I149: EU Biodiversity Strategy for 2030
B150: Marine Ecosystem Restoration | C150: #DBCFC1 | D150: TA6.30 | E150: =ISNUMBER(MATCH(D150,data!A:A)) -> TRUE | F150: =ISNUMBER(MATCH(D150,data!E:E)) -> TRUE | G150: Marine ecosystems. Member States shall put in place [...] measures [...] to jointly cover, as a Union target, throughout the areas and ecosystems [...] defined in Art. 2, by 2030, at least 20% of sea areas in need of restoration and, by 2050, all ecosystems in need of restoration. | H150: Data on restoration has not been systematically collected at the EU level yet. The EU has reached 12% of Marine Protected Areas (MPA), with less than 1% being strictly protected. The target could be partially achieved if the NRL is imme- diately implemented (including a clear financial system), along with the targets of the Biodiversity Strategy (i.e. 30% MPA and 10% strictly protected areas), and if Member States react in a timely manner. The complete achievement of the target also depends on the restoration methods used and the specific marine ecosystems to be restored. The recovery period length varies with the marine habitats targeted for restoration. In addition, Member States face several other challenges in implementing these strategies [205]. The actual implementation of the Biodiversity Strategy target on effective marine protected areas (30% overall and 10% strictly protected by 2030), through passive restoration methods, as well as the other directives such as the Water Framework Directive and the Marine Strategy Framework Directive, and the 2023 Marine Action Plan would contribute to achieving this target. | I150: On the production and marketing of plant reproductive material in the Union, amending Regulations (EU) 2016/2031, 2017/625 and 2018/848 of the European Parliament and of the Council, and repealing Council Directives 66/401/EEC, 66/402/EEC, 68/193/EEC, 2002/53/EC, 2002/54/EC, 2002/55/EC, 2002/56/EC, 2002/57/EC, 2008/72/EC and 2008/90/EC (Regulation on plant reproductive material)
B151: Terrestrial Ecosystems Restoration | C151: #DBCFC1 | D151: TA6.31 | E151: =ISNUMBER(MATCH(D151,data!A:A)) -> TRUE | F151: =ISNUMBER(MATCH(D151,data!E:E)) -> TRUE | G151: Terrestrial, coastal and freshwater ecosystems. Member States shall put in place the restoration measures [...] to improve to good condition areas of habitat types listed in Annex I which are not in good condition. | H151: Protected areas do not necessarily mean that they have a restoration programme. Currently, data on the extension of areas under restoration is not available at the EU level. | I151: On the production and marketing of forest reproductive material, amending Regulations (EU) 2016/2031 and 2017/625 of the European Parliament and of the Council and repealing Council Directive 1999/105/EC (Regulation on forest reproductive material)
... B177: Pesticides Reduction | C177: #DBCFC1 | D177: TA6.9 | E177: =ISNUMBER(MATCH(D177,data!A:A)) -> TRUE | F177: =ISNUMBER(MATCH(D177,data!E:E)) -> TRUE | G177: 6. The risk and use of chemical pesticides is reduced by 50%, and the use of more hazardous pesticides is reduced by 50% | H177: Indicator: Use and risk of chemical pesticides (Source: DG SANTE). According to a trend analysis by DG SANTE, the use and risk of chemical pesticides decreased by 14% between the baseline period of 2015–2017 and 2020. The use and risk of chemical pesticides shows a decrease of 6% from 2020, and an overall decrease in the first four years of observation of 33% from the baseline period of 2015-2017. These overall downward trends shows that the first part of the target can be achieved by 2030 [182]. On the other side, according to data published by DG SANTE, the use of more hazardous pesticides fell by 21% between the baseline period of 2015–2017 and 2021. The use of more hazardous pesticides shows an increase of 5% from 2020 to 2021. Achievement of the 50% reduction target by 2030 remains challenging. It should be noted, while this indicator intends to monitor the use of the more hazardous pesticides, it does not take into account the exposure and hence the impact they might have on the environment and human health. In the future, this indicator should be complemented with a risk indicator showing changes in the actual risks. 1 It should be noted that the current EU-wide indicator, which applies risk weightings to four differ- ent groups of chemical pesticides and is based on pesticide sales, is not considered scientifically robust by some. This indicator is based on a similar harmonised risk indicator, which, according to the European legislation (Commission Directive (EU) 2019/782), is considered hazard-based. This is due to the absence of statistics on the use of plant protection products needed to develop a risk indicator. The Commission is committed to developing more sophisticated indicators in future, such as improved weightings that take hazard properties into account in a more granular way or by using EU-level data on pesticide usage when it becomes available. An example of such an improvement is the new risk indicator assessing the toxicity of pesticide residues in soil from samples collected under the LUCAS Soil Pesticide survey coordinated by JRC. According to this indicator, in 2018, 14% of sites in the EU were at risk of negative effects on soil organisms due to pesticide residues. The analysis of samples from 2022 is currently ongoing and will shed light on the EU’s progress towards pesticide risk reductions. This indicator is relevant to only one compartment (soil) but is just one of many being examined for usefulness and relevance. | I177: EU Biodiversity Strategy for 2030
A178: TA7 - Towards a zero-pollution ambition for a toxic free environment | B178: Improve Water Quality | C178: #FCE4D6 | D178: TA7.10 | E178: =ISNUMBER(MATCH(D178,data!A:A)) -> TRUE | F178: =ISNUMBER(MATCH(D178,data!E:E)) -> TRUE | G178: Improve water quality by reducing waste, plastic litter at sea (by 50%) | H178: Concentration of plastic litter at sea: 14% reduction of plastic litter (in 8% of the basin surface of the Mediterranean Sea and 44% of all beaches) with a total ban on single-use-plastic items. Source: Zero Pollution Outlook [218]. | I178: Pathway to a Healthy Planet for All EU Action Plan: 'Towards Zero Pollution for Air, Water and Soil'
B179: Improve Water Quality | C179: #FCE4D6 | D179: TA7.11 | E179: =ISNUMBER(MATCH(D179,data!A:A)) -> TRUE | F179: =ISNUMBER(MATCH(D179,data!E:E)) -> TRUE | G179: Improve water quality by reducing microplastics released into the environment (by 30%) | H179: Microplastics concentration in soils is expected to increase, mainly due to the incorporation through the disposal of the sewage sludge and other agricultural practices such as plastics greenhouse, mulching films, drip irrigation, polymer-con- trolled release fertilisers and silage films. However, there is no harmonised methodology for their identification and quantification, and one should still be developed. The current database on soil pollution with plastics is still poor and no good prediction could be done. The EU has taken measures to combat microplastic pollution on all fronts (e.g. ban of certain single-use plastic products, restriction of intentionally produced microplastics and reduction of plastic pellet loss), aiming at reducing microplastic releases to the environment by 30% by 2030. | I179: Pathway to a Healthy Planet for All EU Action Plan: 'Towards Zero Pollution for Air, Water and Soil'
B180: Improve Air Quality | C180: #FCE4D6 | D180: TA7.13 | E180: =ISNUMBER(MATCH(D180,data!A:A)) -> TRUE | F180: =ISNUMBER(MATCH(D180,data!E:E)) -> TRUE | G180: Reduce by 25% the EU ecosystems where air pollution threatens biodiversity, by 2030 | H180: Current and proposed EU policies do not appear sufficient to enable the EU to reduce the area of EU ecosystems under threat from air pollution by 25% in 2030 compared to 2005. Nonetheless, with the implementation of the recently revised of the Ambient Air Quality Directives, this target could be achieved. Source: Zero Pollution Outlook [218]. | I180: Pathway to a Healthy Planet for All EU Action Plan: 'Towards Zero Pollution for Air, Water and Soil'
B181: Noise Reduction | C181: #FCE4D6 | D181: TA7.14 | E181: =ISNUMBER(MATCH(D181,data!A:A)) -> TRUE | F181: =ISNUMBER(MATCH(D181,data!E:E)) -> TRUE | G181: Reduce the share of people chronically disturbed by transport noise by 30%, by 2030 | H181: Current estimates show that the number will not decline by more than 19% by 2030. Source: Zero Pollution Outlook [218]. | I181: Pathway to a Healthy Planet for All EU Action Plan: 'Towards Zero Pollution for Air, Water and Soil'
B182: Improve Soils Health | C182: #FCE4D6 | D182: TA7.15 | E182: =ISNUMBER(MATCH(D182,data!A:A)) -> TRUE | F182: =ISNUMBER(MATCH(D182,data!E:E)) -> TRUE | G182: Having all soils in healthy condition by 2050 | H182: The EU Soil Health Assessment (see EUSO Dashboard) estimated that 60-70% of EU soils are not in healthy condition, in accordance also with other reports [196], [238]. 25% of the EU soils and 33% of EU Agricultural soils have soil erosion rates higher than sustainability ones. Soil erosion has decreased by around 10% in the period 2000-2016, but future trends are alarming due to climate change. Soil loss by water erosion is projected to increase by 13–22.5 % in EU and UK by 2050. | I182: Pathway to a Healthy Planet for All EU Action Plan: 'Towards Zero Pollution for Air, Water and Soil'
B183: Improve Water Quality | C183: #FCE4D6 | D183: TA7.16 | E183: =ISNUMBER(MATCH(D183,data!A:A)) -> TRUE | F183: =ISNUMBER(MATCH(D183,data!E:E)) -> TRUE | G183: By means of an updated and harmonised list of pollutants affecting surface and groundwater, updated existing quality standards, new monitoring requirements, improved and more accessible data, and a more flexible framework for addressing pollutants of emerging concerns | H183: Micro-pollutants pose a significant challenge. The necessity of removing them at wastewater treatment facilities increases treatment costs, and complete removal is not always feasible. The proposal encourages more proactive measures upstream by reducing emissions at their source. By avoiding water pollution, the proposal will also benefit the potential for water reuse. The enhanced watch list mechanism requiring Member States to monitor new substances, will enable the Commission, with the support of the European Chemicals Agency and the Member States, to determine the need for additional or stricter quality standards. More frequent reporting of actual monitoring data, and its analysis by the EEA, will provide the EU Institutions, Member States, and the general public with a more precise and current understanding of the status of surface and groundwater bodies in the EU. The analysis of more regular monitoring and status data will effectively feed into the broader Zero Pollution Monitoring and Outlook framework | I183: Pathway to a Healthy Planet for All EU Action Plan: 'Towards Zero Pollution for Air, Water and Soil'
B184: Improve Air Quality | C184: #FCE4D6 | D184: TA7.4 | E184: =ISNUMBER(MATCH(D184,data!A:A)) -> TRUE | F184: =ISNUMBER(MATCH(D184,data!E:E)) -> TRUE | G184: The Industrial Emissions Directive (IED) aims at preventing or reducing emissions from large industrial installations and intensive farming into the environment. | H184: The IED is a key instrument to support the transition of the EU industry towards a climate neutral, clean and circular economy. The revised legislation will lead to a considerable reduction of pollution from industry and level the playing field. For example, it is expected to deliver, latest by 2050, up to 40% additional reduction of key air pollutants. | I184: on the quality of water intended for human consumption
B185: Improve Water Quality | C185: #FCE4D6 | D185: TA7.5 | E185: =ISNUMBER(MATCH(D185,data!A:A)) -> TRUE | F185: =ISNUMBER(MATCH(D185,data!E:E)) -> TRUE | G185: The revised Urban Wastewater Treatment Directive (UWWTD) extends the scope of the 1991 UWWTD | H185: Access to sanitation. There is a positive trend in the access to basic sanitation and connection to secondary wastewater treatment. Overall, the share of population without a bath, shower, or indoor flushing toilet in their household decreased from 2.2% in 2015 to 1.5% in 2020 [234]. However, in some Member States, there were still high shares of the population without access to basic sanitary facilities in 2020. The share of the EU population connected to secondary wastewater treatment has also increased continuously since 2000, reaching 81.1% in 2020 [234]. The revision of the Urban Wastewater Treatment Directive aims to bring additional improvements not only for water quality, but also for access to sanitation [235]. Secondary treatment. Small agglomerations constitute a significant pressure on 11% of the EU’s surface water bodies [236]. Currently, the situation varies across the EU, with some Member States requesting all urban wastewater to be treated and others having set standards for small agglomerations beyond the requirements set in Directive 91/271/EEC [237]. Tertiary treatment. In many cases, nitrogen and phosphorus are well removed from wastewater, but there are still regions where additional removal could bring a significant benefit to the environment. In many cases, the costs of additional removal are well below the benefits that could be achieved, and some wastewater treatment plants operate already beyond the requirements of Directive 91/271/ EEC. The revision of the Directive aims to push nutrient removal further by imposing stricter standards. This would also contribute indirectly to the reduction of GHG emissions. Quaternary treatment. While secondary and tertiary wastewater treatment is being implemented compliant with Directive 91/271/EEC, several chemical micropollutants escape treatment plants and contribute to pollution of the receiving waters (e.g. pharmaceuticals and ingredients in personal care products). The revision of the Directive aims to require quaternary treatment for all larger plants, also based on an extended producer responsibility scheme that would help finance the corresponding treatment costs. | I185: on ambient air quality and cleaner air for Europe
B186: Improve Soils Health | C186: #FCE4D6 | D186: TA7.6 | E186: =ISNUMBER(MATCH(D186,data!A:A)) -> TRUE | F186: =ISNUMBER(MATCH(D186,data!E:E)) -> TRUE | G186: Improve soil quality by reducing chemical pesticides‚Äô use by 50%, by 2030 | H186: Considering soil quality and pesticides, reduction of (more hazardous) pesticide concentration in soil due to increased organic farming (as well as other agricultural practices) and other farm-to-fork objectives. Under current legal limitations (28 kg of copper per hectare over 7 years), a potential risk of increased organic farming could be an accumulation of copper in soil. | I186: Establishing a European assessment framework for ‘safe and sustainable by design’ chemicals and materials
B187: Improve Soils Health | C187: #FCE4D6 | D187: TA7.8 | E187: =ISNUMBER(MATCH(D187,data!A:A)) -> TRUE | F187: =ISNUMBER(MATCH(D187,data!E:E)) -> TRUE | G187: Improve soil quality by reducing nutrient losses use by 50%, by 2030 | H187: Considering water quality and nutrient losses, there is a possible reduction of nutrient inputs into marine ecosystems: nitrogen 32%, phosphorous 17%. 50% reduction of nutrient input could be achieved in four out of ten examined regions for nitrogen and in two out of ten for phosphorous. Source: Zero Pollution Outlook [218]. Considering water quality and chemical pesticides, and in particular chemicals load (diuron and terbuthylazine, as examples of low- and high-persistence chemicals, respectively) in water: 56% reduction in pesticides concentration can be achieved in shelf seas, 12% in open seas, depending on the persistence of the pesticide. Source: Zero Pollution Outlook [218]. | I187: On reporting of environmental data from industrial installations and establishing an Industrial Emissions Portal
B188: Improve Air Quality | C188: #FCE4D6 | D188: TA7.9 | E188: =ISNUMBER(MATCH(D188,data!A:A)) -> TRUE | F188: =ISNUMBER(MATCH(D188,data!E:E)) -> TRUE | G188: Improve air quality to reduce the number of premature deaths caused by air pollution by 55% by 2030 | H188: As a result of the revision to the new Ambient Air Quality Directive, it is likely that reductions by over 70%, compared to 2005 levels, can be achieved by 2030. Source: Zero Pollution Outlook [218]. | I188: Directive 2010/75/EU of the European Parliament and of the Council of 24 November 2010 on industrial emissions (integrated pollution prevention and control) and Council Directive 1999/31/EC of 26 April 1999 on the landfill of waste
